{"big_rounds":[{"match_id":"ace6b80a-5ea2-495e-8587-d8f9ad67b648","round_number":10,"kills":4,"side":"CT","map_name":"de_dust2","played_at":"2026-03-21"},{"match_id":"3ec57ce7-b755-4605-b329-760af846deeb","round_number":9,"kills":4,"side":"CT","map_name":"de_dust2","played_at":"2026-03-13"},{"match_id":"af99ca10-b0ee-4426-aa53-7ca00e82daaf","round_number":7,"kills":4,"side":"CT","map_name":"de_ancient","played_at":"2026-03-07"},{"match_id":"047a488a-e010-4b2b-9f16-69284a0c6f01","round_number":11,"kills":4,"side":"CT","map_name":"de_inferno","played_at":"2026-03-06"},{"match_id":"7d252605-eaf0-48ae-9177-2e83104c074a","round_number":14,"kills":4,"side":"CT","map_name":"de_inferno","played_at":"2026-02-21"},{"match_id":"254bbf99-8cc6-4dcf-9689-e058734f4a8b","round_number":8,"kills":4,"side":"CT","map_name":"de_overpass","played_at":"2025-12-04"},{"match_id":"78c56cce-9aca-4eda-a7f0-151a71f11949","round_number":2,"kills":4,"side":"CT","map_name":"de_overpass","played_at":"2025-12-04"},{"match_id":"243edb24-dd2c-4702-9389-856c0396f378","round_number":14,"kills":4,"side":"T","map_name":"de_ancient","played_at":"2025-11-09"},{"match_id":"54551dda-d0a0-4cd5-a15c-4b5e8090c43e","round_number":5,"kills":4,"side":"CT","map_name":"de_ancient","played_at":"2025-10-06"},{"match_id":"3e3d8fa4-2582-4dba-b54d-79fb86b5004b","round_number":5,"kills":4,"side":"T","map_name":"de_nuke","played_at":"2025-10-04"},{"match_id":"09c5d9ed-309c-44c2-a7ea-4f5470ced608","round_number":10,"kills":4,"side":"CT","map_name":"de_inferno","played_at":"2025-09-05"},{"match_id":"5fefcbaf-0c3d-4ff8-b5f6-5f85b58942f8","round_number":21,"kills":4,"side":"T","map_name":"de_nuke","played_at":"2025-08-14"}],"clutch_moments":[{"match_id":"8a9fb89c-0f06-4e6e-9efa-05062e364327","round_number":15,"versus":4,"won":true,"start_sec":114,"map_name":"de_dust2"},{"match_id":"fde72ae4-f3e5-40e4-a915-6c83378b2f5d","round_number":13,"versus":3,"won":true,"start_sec":91,"map_name":"de_mirage"},{"match_id":"af99ca10-b0ee-4426-aa53-7ca00e82daaf","round_number":25,"versus":2,"won":true,"start_sec":93,"map_name":"de_ancient"},{"match_id":"36759873-efa8-454f-94ea-c116021d142f","round_number":17,"versus":2,"won":true,"start_sec":108,"map_name":"de_mirage"},{"match_id":"53e8dff7-fdb3-4b05-a68f-ffb0bb48d5e6","round_number":6,"versus":2,"won":true,"start_sec":54,"map_name":"de_train"},{"match_id":"d9d4a3fa-cf32-423c-aa36-21f7c2bf16f3","round_number":6,"versus":2,"won":true,"start_sec":62,"map_name":"de_train"},{"match_id":"a094c192-6705-4b97-9255-012622d39d1d","round_number":1,"versus":2,"won":true,"start_sec":49,"map_name":"de_train"},{"match_id":"f54a66d0-c920-44a9-8737-e6b4fadfb3bb","round_number":14,"versus":2,"won":true,"start_sec":96,"map_name":"de_inferno"},{"match_id":"af9d9cfe-1f1c-43c7-9476-4ba9e214669d","round_number":16,"versus":2,"won":true,"start_sec":34,"map_name":"de_mirage"},{"match_id":"05d88059-e9b4-4ef1-99d8-60b7505b874f","round_number":12,"versus":2,"won":true,"start_sec":43,"map_name":"de_ancient"},{"match_id":"e9bd1640-87c4-4cb5-9f64-b16007e3645f","round_number":11,"versus":2,"won":true,"start_sec":77,"map_name":"de_mirage"},{"match_id":"c51a33cb-792c-471a-b2f0-9f4667a076c8","round_number":4,"versus":2,"won":true,"start_sec":63,"map_name":"de_mirage"}],"clutches":[{"versus":1,"attempts":3,"wins":1},{"versus":2,"attempts":74,"wins":13},{"versus":3,"attempts":86,"wins":1},{"versus":4,"attempts":75,"wins":1},{"versus":5,"attempts":42,"wins":0}],"deaths_traded":[{"side":"CT","deaths":783,"traded":175},{"side":"T","deaths":1011,"traded":241}],"flags":[{"metric":"fk_involvement","value":1,"baseline_mean":0.1399505,"baseline_std":0.109090865,"z":7.8837905,"event_name":"mouz-vs-liquid-m1-inferno-p2","map_name":"de_inferno","match_id":"c077a50a-231f-410c-bc69-15f17a3eef99"},{"metric":"traded_death_rate","value":1,"baseline_mean":0.23737009,"baseline_std":0.12685573,"z":6.0117893,"event_name":"g2-vs-mouz-m1-overpass-p1","map_name":"de_overpass","match_id":"2fa0e38b-5a3f-49a8-ac60-dbb86912da90"},{"metric":"fk_involvement","value":0.75,"baseline_mean":0.14160614,"baseline_std":0.11971639,"z":5.0819597,"event_name":"g2-vs-mouz-m2-dust2-p2","map_name":"de_dust2","match_id":"1c40e150-7a0b-48b7-924d-c4cfd2949196"},{"metric":"fk_involvement","value":0.6666667,"baseline_mean":0.14215802,"baseline_std":0.122299775,"z":4.288713,"event_name":"mouz-vs-furia-m2-mirage-p2","map_name":"de_mirage","match_id":"2529c987-c0ff-4f13-bed2-c5bad0c4194a"},{"metric":"fk_involvement","value":0.6,"baseline_mean":0.14259951,"baseline_std":0.12405946,"z":3.6869457,"event_name":"mouz-vs-astralis-m3-overpass-p1","map_name":"de_overpass","match_id":"0e97f3c9-3901-4b0c-ba0f-b6e5d4f1fb2a"},{"metric":"adr","value":0,"baseline_mean":84.04524,"baseline_std":27.952354,"z":-3.0067322,"event_name":"mouz-vs-gentle-mates-m1-inferno-p1","map_name":"de_inferno","match_id":"bdaecc77-d80d-4acf-b601-f1405178a79b"},{"metric":"adr","value":0,"baseline_mean":84.04524,"baseline_std":27.952354,"z":-3.0067322,"event_name":"mouz-vs-liquid-m1-inferno-p2","map_name":"de_inferno","match_id":"c077a50a-231f-410c-bc69-15f17a3eef99"},{"metric":"adr","value":0,"baseline_mean":84.04524,"baseline_std":27.952354,"z":-3.0067322,"event_name":"3dmax-vs-mouz-m1-inferno-p2","map_name":"de_inferno","match_id":"48d53757-51da-4e5d-89c9-723fabee9bb7"},{"metric":"adr","value":0,"baseline_mean":84.04524,"baseline_std":27.952354,"z":-3.0067322,"event_name":"g2-vs-mouz-m1-overpass-p1","map_name":"de_overpass","match_id":"2fa0e38b-5a3f-49a8-ac60-dbb86912da90"},{"metric":"adr","value":166.6875,"baseline_mean":82.94135,"baseline_std":27.95826,"z":2.9953992,"event_name":"mouz-vs-heroic-m3-inferno","map_name":"de_inferno","match_id":"047a488a-e010-4b2b-9f16-69284a0c6f01"},{"metric":"adr","value":4.4,"baseline_mean":84.016106,"baseline_std":28.037529,"z":-2.8396263,"event_name":"mouz-vs-astralis-m3-overpass-p1","map_name":"de_overpass","match_id":"0e97f3c9-3901-4b0c-ba0f-b6e5d4f1fb2a"},{"metric":"fk_involvement","value":0.5,"baseline_mean":0.14326176,"baseline_std":0.12621376,"z":2.8264606,"event_name":"og-vs-mouz-m2-inferno-p1","map_name":"de_inferno","match_id":"94ce79f6-4bf6-4a56-a43b-28b4e9aa449d"},{"metric":"adr","value":162.14285,"baseline_mean":82.97145,"baseline_std":28.045813,"z":2.8229315,"event_name":"mouz-vs-faze-m1-ancient-p1","map_name":"de_ancient","match_id":"a44261e0-c0dd-4c19-8672-7d9bcc9c6b48"},{"metric":"adr","value":140.68182,"baseline_mean":83.11358,"baseline_std":28.390171,"z":2.0277526,"event_name":"mouz-vs-fut-m1-mirage","map_name":"de_mirage","match_id":"746d413f-b2d6-4f15-8e15-73ba345fd4bb"},{"metric":"adr","value":26.666666,"baseline_mean":83.868645,"baseline_std":28.395042,"z":-2.0145059,"event_name":"mouz-vs-furia-m2-mirage-p2","map_name":"de_mirage","match_id":"2529c987-c0ff-4f13-bed2-c5bad0c4194a"},{"metric":"traded_death_rate","value":0.5,"baseline_mean":0.24068135,"baseline_std":0.13955756,"z":1.8581483,"event_name":"mouz-vs-astralis-m3-overpass-p1","map_name":"de_overpass","match_id":"0e97f3c9-3901-4b0c-ba0f-b6e5d4f1fb2a"},{"metric":"traded_death_rate","value":0.5,"baseline_mean":0.24068135,"baseline_std":0.13955756,"z":1.8581483,"event_name":"mouz-vs-heroic-m3-inferno","map_name":"de_inferno","match_id":"047a488a-e010-4b2b-9f16-69284a0c6f01"},{"metric":"traded_death_rate","value":0.5,"baseline_mean":0.24068135,"baseline_std":0.13955756,"z":1.8581483,"event_name":"mouz-vs-aurora-m1-dust2","map_name":"de_dust2","match_id":"646ca280-236d-4d6c-8497-9db1c975f927"},{"metric":"traded_death_rate","value":0.5,"baseline_mean":0.24068135,"baseline_std":0.13955756,"z":1.8581483,"event_name":"legacy-vs-mouz-m3-mirage","map_name":"de_mirage","match_id":"fde72ae4-f3e5-40e4-a915-6c83378b2f5d"},{"metric":"traded_death_rate","value":0.5,"baseline_mean":0.24068135,"baseline_std":0.13955756,"z":1.8581483,"event_name":"falcons-vs-mouz-m1-inferno-p2","map_name":"de_inferno","match_id":"72413f8c-173a-4e67-86ae-9c68ec7b712e"},{"metric":"traded_death_rate","value":0.5,"baseline_mean":0.24068135,"baseline_std":0.13955756,"z":1.8581483,"event_name":"g2-vs-mouz-m1-overpass-p2","map_name":"de_overpass","match_id":"6af7b692-35e9-4962-9a6b-d379f5660418"},{"metric":"traded_death_rate","value":0.5,"baseline_mean":0.24068135,"baseline_std":0.13955756,"z":1.8581483,"event_name":"mouz-vs-furia-m2-mirage-p2","map_name":"de_mirage","match_id":"2529c987-c0ff-4f13-bed2-c5bad0c4194a"},{"metric":"traded_death_rate","value":0,"baseline_mean":0.24399261,"baseline_std":0.13973926,"z":-1.7460563,"event_name":"mouz-vs-gamerlegion-m1-overpass","map_name":"de_overpass","match_id":"ba1921bd-df0a-45b2-a8fa-c8ba45bc058d"},{"metric":"traded_death_rate","value":0,"baseline_mean":0.24399261,"baseline_std":0.13973926,"z":-1.7460563,"event_name":"mouz-vs-fut-m1-dust2","map_name":"de_dust2","match_id":"3ec57ce7-b755-4605-b329-760af846deeb"},{"metric":"traded_death_rate","value":0,"baseline_mean":0.24399261,"baseline_std":0.13973926,"z":-1.7460563,"event_name":"mouz-vs-liquid-m1-inferno-p2","map_name":"de_inferno","match_id":"c077a50a-231f-410c-bc69-15f17a3eef99"},{"metric":"traded_death_rate","value":0,"baseline_mean":0.24399261,"baseline_std":0.13973926,"z":-1.7460563,"event_name":"mouz-vs-parivision-m2-inferno","map_name":"de_inferno","match_id":"f5183fd7-6446-48ce-9b5e-afdf1017e4e2"},{"metric":"traded_death_rate","value":0,"baseline_mean":0.24399261,"baseline_std":0.13973926,"z":-1.7460563,"event_name":"falcons-vs-mouz-m3-nuke-p2","map_name":"de_nuke","match_id":"16b51d42-0e94-4485-9069-c453c9007370"},{"metric":"traded_death_rate","value":0,"baseline_mean":0.24399261,"baseline_std":0.13973926,"z":-1.7460563,"event_name":"g2-vs-mouz-m2-dust2-p2","map_name":"de_dust2","match_id":"1c40e150-7a0b-48b7-924d-c4cfd2949196"},{"metric":"traded_death_rate","value":0,"baseline_mean":0.24399261,"baseline_std":0.13973926,"z":-1.7460563,"event_name":"mouz-vs-gentle-mates-m1-inferno-p1","map_name":"de_inferno","match_id":"bdaecc77-d80d-4acf-b601-f1405178a79b"},{"metric":"traded_death_rate","value":0,"baseline_mean":0.24399261,"baseline_std":0.13973926,"z":-1.7460563,"event_name":"mouz-vs-9z-m2-inferno","map_name":"de_inferno","match_id":"3d25903b-76cd-4346-992b-8a4751c2cb17"},{"metric":"traded_death_rate","value":0,"baseline_mean":0.24399261,"baseline_std":0.13973926,"z":-1.7460563,"event_name":"og-vs-mouz-m2-inferno-p1","map_name":"de_inferno","match_id":"94ce79f6-4bf6-4a56-a43b-28b4e9aa449d"},{"metric":"adr","value":34.5,"baseline_mean":83.816765,"baseline_std":28.492178,"z":-1.7308879,"event_name":"falcons-vs-mouz-m1-inferno-p2","map_name":"de_inferno","match_id":"72413f8c-173a-4e67-86ae-9c68ec7b712e"},{"metric":"adr","value":131.66667,"baseline_mean":83.17328,"baseline_std":28.501474,"z":1.7014344,"event_name":"furia-vs-mouz-m1-inferno","map_name":"de_inferno","match_id":"3b5ddb20-bfdd-401c-844c-e95e29108fbc"},{"metric":"adr","value":131.25,"baseline_mean":83.17604,"baseline_std":28.50615,"z":1.6864419,"event_name":"g2-vs-mouz-m2-dust2-p2","map_name":"de_dust2","match_id":"1c40e150-7a0b-48b7-924d-c4cfd2949196"},{"metric":"adr","value":37.210526,"baseline_mean":83.79881,"baseline_std":28.522373,"z":-1.6333946,"event_name":"mouz-vs-virtus-pro-m1-inferno","map_name":"de_inferno","match_id":"4ffc3fcb-503c-4720-9e11-a7c2ddb4c844"},{"metric":"adr","value":127.2381,"baseline_mean":83.20261,"baseline_std":28.549042,"z":1.5424507,"event_name":"mouz-vs-natus-vincere-m2-inferno","map_name":"de_inferno","match_id":"abf23e76-ee21-4891-b26a-1566e2ba57f3"},{"metric":"adr","value":127,"baseline_mean":83.204185,"baseline_std":28.551466,"z":1.5339253,"event_name":"og-vs-mouz-m2-inferno-p1","map_name":"de_inferno","match_id":"94ce79f6-4bf6-4a56-a43b-28b4e9aa449d"},{"metric":"adr","value":126.73913,"baseline_mean":83.20591,"baseline_std":28.55411,"z":1.5245869,"event_name":"mouz-vs-virtus-pro-m3-overpass","map_name":"de_overpass","match_id":"6a75d469-a3d2-48d6-98eb-f59777a46e9e"},{"metric":"adr","value":126.1875,"baseline_mean":83.209564,"baseline_std":28.559643,"z":1.5048485,"event_name":"mouz-vs-gamerlegion-m2-nuke","map_name":"de_nuke","match_id":"3e3d8fa4-2582-4dba-b54d-79fb86b5004b"},{"metric":"adr","value":40.8125,"baseline_mean":83.77496,"baseline_std":28.559795,"z":-1.5042987,"event_name":"3dmax-vs-mouz-m1-inferno-p1","map_name":"de_inferno","match_id":"213ec967-6cd8-48df-8798-6f80c4363504"}],"flash":[{"side":"T","thrown":575,"enemies":424,"teammates":499,"avg_blind":2.4},{"side":"CT","thrown":533,"enemies":396,"teammates":384,"avg_blind":2.4}],"maps":[{"map_name":"de_inferno","rounds":676,"matches":38,"adr":81.5,"kills":402,"deaths":390,"assists":142,"survival_pct":43},{"map_name":"de_mirage","rounds":651,"matches":33,"adr":84.9,"kills":412,"deaths":379,"assists":146,"survival_pct":42},{"map_name":"de_ancient","rounds":389,"matches":19,"adr":87.6,"kills":251,"deaths":244,"assists":93,"survival_pct":38},{"map_name":"de_overpass","rounds":366,"matches":19,"adr":95.5,"kills":241,"deaths":234,"assists":84,"survival_pct":37},{"map_name":"de_nuke","rounds":336,"matches":17,"adr":91.5,"kills":216,"deaths":216,"assists":67,"survival_pct":37},{"map_name":"de_dust2","rounds":334,"matches":16,"adr":78.6,"kills":193,"deaths":214,"assists":68,"survival_pct":36},{"map_name":"de_train","rounds":215,"matches":10,"adr":95.0,"kills":151,"deaths":117,"assists":47,"survival_pct":46}],"nickname":"Jimpphat","openings":[{"map_name":"de_ancient","won":31,"lost":29},{"map_name":"de_dust2","won":31,"lost":24},{"map_name":"de_inferno","won":48,"lost":32},{"map_name":"de_mirage","won":36,"lost":38},{"map_name":"de_nuke","won":20,"lost":27},{"map_name":"de_overpass","won":29,"lost":30},{"map_name":"de_train","won":19,"lost":8}],"player_id":"987f74e0-4050-55f8-a6d6-d3a1d2971d7e","roles":[{"side":"T","map_name":"","rounds":1464,"entry_attempt_share":0.125,"entry_success":0.4262295,"opening_kills":78,"opening_deaths":105,"lurk_dist_avg":698.0215,"anchor_place":"Apartments (inferno)","anchor_share":0.3747707,"awp_round_share":0.046831954,"util_per_round":1.7411202,"flash_assists_pr":0,"adr":84.1291,"tags":[]},{"side":"CT","map_name":"","rounds":1503,"entry_attempt_share":0.14570858,"entry_success":0.6210046,"opening_kills":136,"opening_deaths":83,"lurk_dist_avg":1039.6084,"anchor_place":"BombsiteA (inferno)","anchor_share":0.24213807,"awp_round_share":0.05,"util_per_round":2.1104457,"flash_assists_pr":0,"adr":88.93679,"tags":[]},{"side":"T","map_name":"de_ancient","rounds":176,"entry_attempt_share":0.125,"entry_success":0.4090909,"opening_kills":9,"opening_deaths":13,"lurk_dist_avg":672.032,"anchor_place":"Outside","anchor_share":0.19885413,"awp_round_share":0.09248555,"util_per_round":2.0113637,"flash_assists_pr":0,"adr":84.619316,"tags":[]},{"side":"CT","map_name":"de_ancient","rounds":213,"entry_attempt_share":0.17840375,"entry_success":0.57894737,"opening_kills":22,"opening_deaths":16,"lurk_dist_avg":807.72015,"anchor_place":"SideHall","anchor_share":0.34465405,"awp_round_share":0.04694836,"util_per_round":2.2159624,"flash_assists_pr":0,"adr":90.098595,"tags":[]},{"side":"T","map_name":"de_dust2","rounds":147,"entry_attempt_share":0.14965986,"entry_success":0.5,"opening_kills":11,"opening_deaths":11,"lurk_dist_avg":760.588,"anchor_place":"OutsideLong","anchor_share":0.23065482,"awp_round_share":0.04109589,"util_per_round":1.7482994,"flash_assists_pr":0,"adr":69.918365,"tags":[]},{"side":"CT","map_name":"de_dust2","rounds":187,"entry_attempt_share":0.1764706,"entry_success":0.6060606,"opening_kills":20,"opening_deaths":13,"lurk_dist_avg":1308.8827,"anchor_place":"BombsiteB","anchor_share":0.5360601,"awp_round_share":0.10106383,"util_per_round":2.4545455,"flash_assists_pr":0,"adr":85.481285,"tags":["ANCHOR:BombsiteB"]},{"side":"T","map_name":"de_inferno","rounds":351,"entry_attempt_share":0.09686609,"entry_success":0.47058824,"opening_kills":16,"opening_deaths":18,"lurk_dist_avg":754.51556,"anchor_place":"Apartments","anchor_share":0.3747707,"awp_round_share":0.04597701,"util_per_round":1.5555556,"flash_assists_pr":0,"adr":76.20798,"tags":["LURKER"]},{"side":"CT","map_name":"de_inferno","rounds":325,"entry_attempt_share":0.14153846,"entry_success":0.6956522,"opening_kills":32,"opening_deaths":14,"lurk_dist_avg":1235.2074,"anchor_place":"BombsiteA","anchor_share":0.24213807,"awp_round_share":0.03405573,"util_per_round":1.8676924,"flash_assists_pr":0,"adr":87.28,"tags":[]},{"side":"T","map_name":"de_mirage","rounds":337,"entry_attempt_share":0.118694365,"entry_success":0.475,"opening_kills":19,"opening_deaths":21,"lurk_dist_avg":855.69556,"anchor_place":"PalaceInterior","anchor_share":0.37164357,"awp_round_share":0.038575668,"util_per_round":1.7299703,"flash_assists_pr":0,"adr":89.79228,"tags":[]},{"side":"CT","map_name":"de_mirage","rounds":314,"entry_attempt_share":0.10828026,"entry_success":0.5,"opening_kills":17,"opening_deaths":17,"lurk_dist_avg":1204.3502,"anchor_place":"BombsiteB","anchor_share":0.29718995,"awp_round_share":0.041533545,"util_per_round":2.178344,"flash_assists_pr":0,"adr":79.60191,"tags":[]},{"side":"T","map_name":"de_nuke","rounds":175,"entry_attempt_share":0.14285715,"entry_success":0.32,"opening_kills":8,"opening_deaths":17,"lurk_dist_avg":464.75696,"anchor_place":"Lobby","anchor_share":0.20799968,"awp_round_share":0.040697675,"util_per_round":1.88,"flash_assists_pr":0,"adr":85.262856,"tags":[]},{"side":"CT","map_name":"de_nuke","rounds":161,"entry_attempt_share":0.13664596,"entry_success":0.54545456,"opening_kills":12,"opening_deaths":10,"lurk_dist_avg":737.2457,"anchor_place":"Ramp","anchor_share":0.41320732,"awp_round_share":0.031055901,"util_per_round":1.8509316,"flash_assists_pr":0,"adr":98.347824,"tags":[]},{"side":"T","map_name":"de_overpass","rounds":171,"entry_attempt_share":0.16374269,"entry_success":0.2857143,"opening_kills":8,"opening_deaths":20,"lurk_dist_avg":386.02557,"anchor_place":"Tunnels","anchor_share":0.21010073,"awp_round_share":0.0295858,"util_per_round":1.5497077,"flash_assists_pr":0,"adr":88.90058,"tags":[]},{"side":"CT","map_name":"de_overpass","rounds":195,"entry_attempt_share":0.15897436,"entry_success":0.67741936,"opening_kills":21,"opening_deaths":10,"lurk_dist_avg":875.9442,"anchor_place":"BombsiteB","anchor_share":0.38193902,"awp_round_share":0.041025642,"util_per_round":2.2871795,"flash_assists_pr":0,"adr":101.22564,"tags":[]},{"side":"T","map_name":"de_train","rounds":107,"entry_attempt_share":0.11214953,"entry_success":0.5833333,"opening_kills":7,"opening_deaths":5,"lurk_dist_avg":835.37195,"anchor_place":"Ivy","anchor_share":0.2292197,"awp_round_share":0.046728972,"util_per_round":2.0093458,"flash_assists_pr":0,"adr":101.514015,"tags":["LURKER"]},{"side":"CT","map_name":"de_train","rounds":108,"entry_attempt_share":0.1388889,"entry_success":0.8,"opening_kills":12,"opening_deaths":3,"lurk_dist_avg":689.842,"anchor_place":"Tunnels","anchor_share":0.3336816,"awp_round_share":0.08411215,"util_per_round":1.9074074,"flash_assists_pr":0,"adr":88.53704,"tags":[]}],"team":"MOUZ","trades":[{"side":"CT","made":153},{"side":"T","made":256}],"util_dmg":[{"side":"T","he_dmg":2354,"fire_dmg":1769,"he_n":438,"fire_n":675},{"side":"CT","he_dmg":4520,"fire_dmg":1737,"he_n":761,"fire_n":869}]}
