{"boosts":[],"conditional":[{"side":"CT","buy_type":"force","cluster_id":2,"label":null,"top_places":[{"place":"Banana","weight":0.19},{"place":"BombsiteA","weight":0.137},{"place":"BombsiteB","weight":0.133},{"place":"TopofMid","weight":0.084},{"place":"Arch","weight":0.072}],"prob":0.39537830466250024,"sample_size":1},{"side":"CT","buy_type":"full","cluster_id":2,"label":null,"top_places":[{"place":"Banana","weight":0.19},{"place":"BombsiteA","weight":0.137},{"place":"BombsiteB","weight":0.133},{"place":"TopofMid","weight":0.084},{"place":"Arch","weight":0.072}],"prob":0.44497204504291676,"sample_size":20},{"side":"CT","buy_type":"pistol","cluster_id":1,"label":null,"top_places":[{"place":"BombsiteA","weight":0.15},{"place":"BombsiteB","weight":0.127},{"place":"TopofMid","weight":0.1},{"place":"Banana","weight":0.1},{"place":"Apartments","weight":0.068}],"prob":0.37416331994645247,"sample_size":2},{"side":"CT","buy_type":"semi","cluster_id":2,"label":null,"top_places":[{"place":"Banana","weight":0.19},{"place":"BombsiteA","weight":0.137},{"place":"BombsiteB","weight":0.133},{"place":"TopofMid","weight":0.084},{"place":"Arch","weight":0.072}],"prob":0.39537830466250024,"sample_size":1},{"side":"T","buy_type":"eco","cluster_id":1,"label":null,"top_places":[{"place":"TRamp","weight":0.181},{"place":"SecondMid","weight":0.177},{"place":"LowerMid","weight":0.138},{"place":"Middle","weight":0.086},{"place":"Apartments","weight":0.066}],"prob":0.42228808281253355,"sample_size":1},{"side":"T","buy_type":"force","cluster_id":2,"label":null,"top_places":[{"place":"Banana","weight":0.346},{"place":"TRamp","weight":0.124},{"place":"LowerMid","weight":0.099},{"place":"SecondMid","weight":0.084},{"place":"Middle","weight":0.077}],"prob":0.4739743286872982,"sample_size":2},{"side":"T","buy_type":"full","cluster_id":2,"label":null,"top_places":[{"place":"Banana","weight":0.346},{"place":"TRamp","weight":0.124},{"place":"LowerMid","weight":0.099},{"place":"SecondMid","weight":0.084},{"place":"Middle","weight":0.077}],"prob":0.48580417928398084,"sample_size":12},{"side":"T","buy_type":"pistol","cluster_id":2,"label":null,"top_places":[{"place":"Banana","weight":0.346},{"place":"TRamp","weight":0.124},{"place":"LowerMid","weight":0.099},{"place":"SecondMid","weight":0.084},{"place":"Middle","weight":0.077}],"prob":0.3906409953539649,"sample_size":2},{"side":"T","buy_type":"semi","cluster_id":1,"label":null,"top_places":[{"place":"TRamp","weight":0.181},{"place":"SecondMid","weight":0.177},{"place":"LowerMid","weight":0.138},{"place":"Middle","weight":0.086},{"place":"Apartments","weight":0.066}],"prob":0.42228808281253355,"sample_size":1}],"economy":{"after_pistol_loss":{"eco":1,"force":1},"buy_CT":{"force":1,"full":20,"semi":1},"buy_T":{"eco":1,"force":2,"full":12,"semi":1}},"exec_templates":[],"flash_sync":[{"side":"T","kills":68,"blind_kills":15,"med_gap":1.28125,"good_flashes":24,"converted":11},{"side":"CT","kills":86,"blind_kills":16,"med_gap":2.0625,"good_flashes":52,"converted":13}],"map":"de_inferno","overview":{"matches":2,"wins":2,"t_rounds":18,"t_wins":13,"ct_rounds":24,"ct_wins":13,"pistol_rounds":4,"pistol_wins":2,"conv_after_pistol_win_n":2,"conv_after_pistol_win":1},"playbook":{"rush_n":6,"rush_total":18,"setstrat_rounds":0,"t_rounds_all":18},"players":[],"rotations":[{"side":"T","pattern_id":0,"place":"SecondMid","n_contacts":7,"rotate_rate":1,"med_delay_sec":1.84375,"dest_mix":{"Arch":1,"Underpass":1,"Apartments":4}},{"side":"T","pattern_id":0,"place":"Banana","n_contacts":8,"rotate_rate":0.5,"med_delay_sec":1.8515625,"dest_mix":{"Arch":1,"TRamp":1,"Middle":2}},{"side":"T","pattern_id":1,"place":"Banana","n_contacts":6,"rotate_rate":0.33333334,"med_delay_sec":3.5703125,"dest_mix":{"Middle":1,"BombsiteB":1}}],"round_tendencies":[{"rclass":"3rd round","side":"T","cluster_id":0,"label":null,"top_places":[{"place":"Middle","weight":0.247},{"place":"SecondMid","weight":0.156},{"place":"TRamp","weight":0.116},{"place":"LowerMid","weight":0.082},{"place":"Apartments","weight":0.081}],"n":1,"total":2,"share":0.50},{"rclass":"3rd round","side":"T","cluster_id":2,"label":null,"top_places":[{"place":"Banana","weight":0.346},{"place":"TRamp","weight":0.124},{"place":"LowerMid","weight":0.099},{"place":"SecondMid","weight":0.084},{"place":"Middle","weight":0.077}],"n":1,"total":2,"share":0.50},{"rclass":"after pistol","side":"T","cluster_id":1,"label":null,"top_places":[{"place":"TRamp","weight":0.181},{"place":"SecondMid","weight":0.177},{"place":"LowerMid","weight":0.138},{"place":"Middle","weight":0.086},{"place":"Apartments","weight":0.066}],"n":1,"total":2,"share":0.50},{"rclass":"after pistol","side":"T","cluster_id":2,"label":null,"top_places":[{"place":"Banana","weight":0.346},{"place":"TRamp","weight":0.124},{"place":"LowerMid","weight":0.099},{"place":"SecondMid","weight":0.084},{"place":"Middle","weight":0.077}],"n":1,"total":2,"share":0.50},{"rclass":"mid-game","side":"T","cluster_id":2,"label":null,"top_places":[{"place":"Banana","weight":0.346},{"place":"TRamp","weight":0.124},{"place":"LowerMid","weight":0.099},{"place":"SecondMid","weight":0.084},{"place":"Middle","weight":0.077}],"n":7,"total":12,"share":0.58},{"rclass":"mid-game","side":"T","cluster_id":0,"label":null,"top_places":[{"place":"Middle","weight":0.247},{"place":"SecondMid","weight":0.156},{"place":"TRamp","weight":0.116},{"place":"LowerMid","weight":0.082},{"place":"Apartments","weight":0.081}],"n":3,"total":12,"share":0.25},{"rclass":"pistol","side":"T","cluster_id":1,"label":null,"top_places":[{"place":"TRamp","weight":0.181},{"place":"SecondMid","weight":0.177},{"place":"LowerMid","weight":0.138},{"place":"Middle","weight":0.086},{"place":"Apartments","weight":0.066}],"n":1,"total":2,"share":0.50},{"rclass":"pistol","side":"T","cluster_id":2,"label":null,"top_places":[{"place":"Banana","weight":0.346},{"place":"TRamp","weight":0.124},{"place":"LowerMid","weight":0.099},{"place":"SecondMid","weight":0.084},{"place":"Middle","weight":0.077}],"n":1,"total":2,"share":0.50},{"rclass":"3rd round","side":"CT","cluster_id":1,"label":null,"top_places":[{"place":"BombsiteA","weight":0.15},{"place":"BombsiteB","weight":0.127},{"place":"TopofMid","weight":0.1},{"place":"Banana","weight":0.1},{"place":"Apartments","weight":0.068}],"n":1,"total":2,"share":0.50},{"rclass":"3rd round","side":"CT","cluster_id":2,"label":null,"top_places":[{"place":"Banana","weight":0.19},{"place":"BombsiteA","weight":0.137},{"place":"BombsiteB","weight":0.133},{"place":"TopofMid","weight":0.084},{"place":"Arch","weight":0.072}],"n":1,"total":2,"share":0.50},{"rclass":"after pistol","side":"CT","cluster_id":1,"label":null,"top_places":[{"place":"BombsiteA","weight":0.15},{"place":"BombsiteB","weight":0.127},{"place":"TopofMid","weight":0.1},{"place":"Banana","weight":0.1},{"place":"Apartments","weight":0.068}],"n":1,"total":2,"share":0.50},{"rclass":"after pistol","side":"CT","cluster_id":2,"label":null,"top_places":[{"place":"Banana","weight":0.19},{"place":"BombsiteA","weight":0.137},{"place":"BombsiteB","weight":0.133},{"place":"TopofMid","weight":0.084},{"place":"Arch","weight":0.072}],"n":1,"total":2,"share":0.50},{"rclass":"mid-game","side":"CT","cluster_id":0,"label":null,"top_places":[{"place":"BombsiteB","weight":0.304},{"place":"BombsiteA","weight":0.127},{"place":"TopofMid","weight":0.076},{"place":"Ruins","weight":0.066},{"place":"Apartments","weight":0.064}],"n":10,"total":18,"share":0.56},{"rclass":"mid-game","side":"CT","cluster_id":2,"label":null,"top_places":[{"place":"Banana","weight":0.19},{"place":"BombsiteA","weight":0.137},{"place":"BombsiteB","weight":0.133},{"place":"TopofMid","weight":0.084},{"place":"Arch","weight":0.072}],"n":7,"total":18,"share":0.39},{"rclass":"pistol","side":"CT","cluster_id":1,"label":null,"top_places":[{"place":"BombsiteA","weight":0.15},{"place":"BombsiteB","weight":0.127},{"place":"TopofMid","weight":0.1},{"place":"Banana","weight":0.1},{"place":"Apartments","weight":0.068}],"n":2,"total":2,"share":1.00}],"setups":[{"side":"CT","t_offset":30,"pattern_id":0,"pattern":[{"n":1,"place":"Balcony"},{"n":2,"place":"Banana"},{"n":1,"place":"BombsiteA"},{"n":1,"place":"Library"}],"observed":2,"sample_size":20,"share":0.10044498,"avg_hold_sec":16.5,"representatives":[{"match_id":"b2ac333a-f3c5-4a46-969f-edc61aa9052a","round_number":5},{"match_id":"b2ac333a-f3c5-4a46-969f-edc61aa9052a","round_number":3}]},{"side":"CT","t_offset":30,"pattern_id":1,"pattern":[{"n":2,"place":"BombsiteA"},{"n":1,"place":"BombsiteB"},{"n":1,"place":"Pit"},{"n":1,"place":"Ruins"}],"observed":2,"sample_size":20,"share":0.10044498,"avg_hold_sec":8,"representatives":[{"match_id":"b2ac333a-f3c5-4a46-969f-edc61aa9052a","round_number":9},{"match_id":"b2ac333a-f3c5-4a46-969f-edc61aa9052a","round_number":10}]},{"side":"CT","t_offset":30,"pattern_id":2,"pattern":[{"n":1,"place":"Apartments"},{"n":1,"place":"BombsiteA"},{"n":2,"place":"BombsiteB"},{"n":1,"place":"CTSpawn"}],"observed":2,"sample_size":20,"share":0.10004045,"avg_hold_sec":11.5,"representatives":[{"match_id":"b2ac333a-f3c5-4a46-969f-edc61aa9052a","round_number":11},{"match_id":"adee609d-82e2-44f0-b92e-b5df529d2968","round_number":3}]},{"side":"T","t_offset":15,"pattern_id":0,"pattern":[{"n":2,"place":"Banana"},{"n":2,"place":"SecondMid"},{"n":1,"place":"TRamp"}],"observed":4,"sample_size":18,"share":0.22252215,"avg_hold_sec":7.5,"representatives":[{"match_id":"b2ac333a-f3c5-4a46-969f-edc61aa9052a","round_number":13},{"match_id":"adee609d-82e2-44f0-b92e-b5df529d2968","round_number":16},{"match_id":"adee609d-82e2-44f0-b92e-b5df529d2968","round_number":15}]},{"side":"T","t_offset":15,"pattern_id":1,"pattern":[{"n":3,"place":"Banana"},{"n":1,"place":"SecondMid"},{"n":1,"place":"TRamp"}],"observed":2,"sample_size":18,"share":0.11126108,"avg_hold_sec":9,"representatives":[{"match_id":"b2ac333a-f3c5-4a46-969f-edc61aa9052a","round_number":16},{"match_id":"adee609d-82e2-44f0-b92e-b5df529d2968","round_number":21}]}],"team":"LGCY","team_id":"8a4b343b-0058-414c-a198-2c9459f50578","tendencies":[{"side":"CT","cluster_id":2,"label":null,"top_places":[{"place":"Banana","weight":0.19},{"place":"BombsiteA","weight":0.137},{"place":"BombsiteB","weight":0.133},{"place":"TopofMid","weight":0.084},{"place":"Arch","weight":0.072}],"observed":9,"sample_size":24,"prob":0.40223460687670465},{"side":"CT","cluster_id":0,"label":null,"top_places":[{"place":"BombsiteB","weight":0.304},{"place":"BombsiteA","weight":0.127},{"place":"TopofMid","weight":0.076},{"place":"Ruins","weight":0.066},{"place":"Apartments","weight":0.064}],"observed":10,"sample_size":24,"prob":0.37094903678886665},{"side":"CT","cluster_id":1,"label":null,"top_places":[{"place":"BombsiteA","weight":0.15},{"place":"BombsiteB","weight":0.127},{"place":"TopofMid","weight":0.1},{"place":"Banana","weight":0.1},{"place":"Apartments","weight":0.068}],"observed":5,"sample_size":24,"prob":0.22681635633442862},{"side":"T","cluster_id":2,"label":null,"top_places":[{"place":"Banana","weight":0.346},{"place":"TRamp","weight":0.124},{"place":"LowerMid","weight":0.099},{"place":"SecondMid","weight":0.084},{"place":"Middle","weight":0.077}],"observed":10,"sample_size":18,"prob":0.4572469444340831},{"side":"T","cluster_id":1,"label":null,"top_places":[{"place":"TRamp","weight":0.181},{"place":"SecondMid","weight":0.177},{"place":"LowerMid","weight":0.138},{"place":"Middle","weight":0.086},{"place":"Apartments","weight":0.066}],"observed":4,"sample_size":18,"prob":0.29711415320725626},{"side":"T","cluster_id":0,"label":null,"top_places":[{"place":"Middle","weight":0.247},{"place":"SecondMid","weight":0.156},{"place":"TRamp","weight":0.116},{"place":"LowerMid","weight":0.082},{"place":"Apartments","weight":0.081}],"observed":4,"sample_size":18,"prob":0.24563890235866062}],"thrown":[{"match_id":"adee609d-82e2-44f0-b92e-b5df529d2968","round_number":23,"side":"T","peak":0.9269815},{"match_id":"adee609d-82e2-44f0-b92e-b5df529d2968","round_number":3,"side":"CT","peak":0.9259287},{"match_id":"b2ac333a-f3c5-4a46-969f-edc61aa9052a","round_number":16,"side":"T","peak":0.9224755},{"match_id":"b2ac333a-f3c5-4a46-969f-edc61aa9052a","round_number":8,"side":"CT","peak":0.90295154},{"match_id":"adee609d-82e2-44f0-b92e-b5df529d2968","round_number":5,"side":"CT","peak":0.89832264}],"trade_pairs":[{"trader":"arT","avenged":"n1ssim","n":3},{"trader":"dumau","avenged":"arT","n":2},{"trader":"arT","avenged":"dumau","n":2},{"trader":"latto","avenged":"arT","n":2},{"trader":"latto","avenged":"dumau","n":2},{"trader":"saadzin","avenged":"n1ssim","n":2},{"trader":"dumau","avenged":"saadzin","n":2}],"util_dmg":[{"side":"T","he_dmg":445,"fire_dmg":39,"he_n":47,"fire_n":52},{"side":"CT","he_dmg":1274,"fire_dmg":191,"he_n":83,"fire_n":70}],"utility":[{"side":"CT","type":"flash","cluster_id":0,"label":"Banana","det_rx":525.65656,"det_ry":357.1446,"throw_rx":591.549,"throw_ry":255.65997,"count":32,"share":0.35138774,"t_avg":17.933105,"t_std":20.346706,"strat_mix":{"0":14,"1":4,"2":14},"representatives":[{"match_id":"adee609d-82e2-44f0-b92e-b5df529d2968","round_number":2},{"match_id":"adee609d-82e2-44f0-b92e-b5df529d2968","round_number":3},{"match_id":"adee609d-82e2-44f0-b92e-b5df529d2968","round_number":4}]},{"side":"CT","type":"flash","cluster_id":1,"label":"Banana","det_rx":599.6965,"det_ry":354.7685,"throw_rx":546.18317,"throw_ry":218.61931,"count":11,"share":0.120597996,"t_avg":34.840908,"t_std":23.390478,"strat_mix":{"0":8,"1":3},"representatives":[{"match_id":"adee609d-82e2-44f0-b92e-b5df529d2968","round_number":2},{"match_id":"adee609d-82e2-44f0-b92e-b5df529d2968","round_number":3},{"match_id":"adee609d-82e2-44f0-b92e-b5df529d2968","round_number":4}]},{"side":"CT","type":"flash","cluster_id":2,"label":"BombsiteB","det_rx":570.8111,"det_ry":240.37521,"throw_rx":705.3841,"throw_ry":244.4322,"count":10,"share":0.11019173,"t_avg":73.04375,"t_std":27.061193,"strat_mix":{"0":9,"2":1},"representatives":[{"match_id":"adee609d-82e2-44f0-b92e-b5df529d2968","round_number":10},{"match_id":"b2ac333a-f3c5-4a46-969f-edc61aa9052a","round_number":2},{"match_id":"b2ac333a-f3c5-4a46-969f-edc61aa9052a","round_number":8}]},{"side":"CT","type":"flash","cluster_id":3,"label":"Balcony","det_rx":808.4803,"det_ry":840.0103,"throw_rx":901.7797,"throw_ry":646.3564,"count":8,"share":0.08813562,"t_avg":50.882812,"t_std":22.036293,"strat_mix":{"0":3,"2":5},"representatives":[{"match_id":"adee609d-82e2-44f0-b92e-b5df529d2968","round_number":11},{"match_id":"b2ac333a-f3c5-4a46-969f-edc61aa9052a","round_number":4},{"match_id":"b2ac333a-f3c5-4a46-969f-edc61aa9052a","round_number":4}]},{"side":"CT","type":"flash","cluster_id":4,"label":"BombsiteB","det_rx":513.4494,"det_ry":194.65306,"throw_rx":679.28314,"throw_ry":229.94614,"count":7,"share":0.07692991,"t_avg":83.252235,"t_std":23.962282,"strat_mix":{"0":5,"2":2},"representatives":[{"match_id":"adee609d-82e2-44f0-b92e-b5df529d2968","round_number":4},{"match_id":"adee609d-82e2-44f0-b92e-b5df529d2968","round_number":5},{"match_id":"adee609d-82e2-44f0-b92e-b5df529d2968","round_number":6}]},{"side":"CT","type":"flash","cluster_id":5,"label":"Library","det_rx":917.6334,"det_ry":539.6324,"throw_rx":859.6504,"throw_ry":432.62643,"count":5,"share":0.055051453,"t_avg":48.078125,"t_std":5.112886,"strat_mix":{"0":3,"1":1,"2":1},"representatives":[{"match_id":"adee609d-82e2-44f0-b92e-b5df529d2968","round_number":3},{"match_id":"b2ac333a-f3c5-4a46-969f-edc61aa9052a","round_number":10},{"match_id":"b2ac333a-f3c5-4a46-969f-edc61aa9052a","round_number":11}]},{"side":"CT","type":"flash","cluster_id":6,"label":"TopofMid","det_rx":644.7831,"det_ry":676.08356,"throw_rx":741.0293,"throw_ry":711.9418,"count":4,"share":0.043845743,"t_avg":13.402344,"t_std":3.0214155,"strat_mix":{"0":3,"2":1},"representatives":[{"match_id":"adee609d-82e2-44f0-b92e-b5df529d2968","round_number":6},{"match_id":"adee609d-82e2-44f0-b92e-b5df529d2968","round_number":9},{"match_id":"adee609d-82e2-44f0-b92e-b5df529d2968","round_number":10}]},{"side":"CT","type":"flash","cluster_id":7,"label":"Banana","det_rx":419.60135,"det_ry":499.59036,"throw_rx":580.3173,"throw_ry":338.75754,"count":3,"share":0.03299534,"t_avg":22.328125,"t_std":3.5246296,"strat_mix":{"2":3},"representatives":[{"match_id":"adee609d-82e2-44f0-b92e-b5df529d2968","round_number":8},{"match_id":"b2ac333a-f3c5-4a46-969f-edc61aa9052a","round_number":2},{"match_id":"b2ac333a-f3c5-4a46-969f-edc61aa9052a","round_number":5}]},{"side":"CT","type":"flash","cluster_id":8,"label":"Arch","det_rx":837.86206,"det_ry":549.29456,"throw_rx":907.82697,"throw_ry":676.77734,"count":3,"share":0.032906514,"t_avg":65.02604,"t_std":6.1737843,"strat_mix":{"0":1,"2":2},"representatives":[{"match_id":"adee609d-82e2-44f0-b92e-b5df529d2968","round_number":5},{"match_id":"adee609d-82e2-44f0-b92e-b5df529d2968","round_number":10},{"match_id":"b2ac333a-f3c5-4a46-969f-edc61aa9052a","round_number":5}]},{"side":"CT","type":"he","cluster_id":0,"label":"Banana","det_rx":458.11255,"det_ry":500.65784,"throw_rx":591.0146,"throw_ry":323.6509,"count":24,"share":0.28940663,"t_avg":10.190755,"t_std":1.6859318,"strat_mix":{"0":12,"1":3,"2":9},"representatives":[{"match_id":"adee609d-82e2-44f0-b92e-b5df529d2968","round_number":2},{"match_id":"adee609d-82e2-44f0-b92e-b5df529d2968","round_number":4},{"match_id":"adee609d-82e2-44f0-b92e-b5df529d2968","round_number":5}]},{"side":"CT","type":"he","cluster_id":1,"label":"Banana","det_rx":503.91824,"det_ry":417.47803,"throw_rx":554.5997,"throw_ry":268.51263,"count":23,"share":0.27682438,"t_avg":27.480978,"t_std":11.121019,"strat_mix":{"0":12,"1":7,"2":4},"representatives":[{"match_id":"adee609d-82e2-44f0-b92e-b5df529d2968","round_number":1},{"match_id":"adee609d-82e2-44f0-b92e-b5df529d2968","round_number":2},{"match_id":"adee609d-82e2-44f0-b92e-b5df529d2968","round_number":2}]},{"side":"CT","type":"he","cluster_id":2,"label":"TRamp","det_rx":454.35553,"det_ry":554.5273,"throw_rx":586.30255,"throw_ry":326.51093,"count":6,"share":0.07208375,"t_avg":12.4973955,"t_std":3.7577438,"strat_mix":{"0":3,"1":1,"2":2},"representatives":[{"match_id":"adee609d-82e2-44f0-b92e-b5df529d2968","round_number":3},{"match_id":"adee609d-82e2-44f0-b92e-b5df529d2968","round_number":7},{"match_id":"adee609d-82e2-44f0-b92e-b5df529d2968","round_number":10}]},{"side":"CT","type":"he","cluster_id":3,"label":"TRamp","det_rx":430.9675,"det_ry":630.8257,"throw_rx":636.0309,"throw_ry":572.1111,"count":5,"share":0.060086027,"t_avg":16.434376,"t_std":7.464561,"strat_mix":{"0":3,"2":2},"representatives":[{"match_id":"adee609d-82e2-44f0-b92e-b5df529d2968","round_number":9},{"match_id":"adee609d-82e2-44f0-b92e-b5df529d2968","round_number":10},{"match_id":"adee609d-82e2-44f0-b92e-b5df529d2968","round_number":10}]},{"side":"CT","type":"he","cluster_id":4,"label":"TopofMid","det_rx":651.4877,"det_ry":682.3226,"throw_rx":739.6693,"throw_ry":591.79315,"count":4,"share":0.048283152,"t_avg":25.304688,"t_std":12.516457,"strat_mix":{"2":4},"representatives":[{"match_id":"adee609d-82e2-44f0-b92e-b5df529d2968","round_number":5},{"match_id":"b2ac333a-f3c5-4a46-969f-edc61aa9052a","round_number":2},{"match_id":"b2ac333a-f3c5-4a46-969f-edc61aa9052a","round_number":7}]},{"side":"CT","type":"he","cluster_id":5,"label":"Banana","det_rx":578.08246,"det_ry":391.7736,"throw_rx":538.4335,"throw_ry":186.89217,"count":4,"share":0.048283152,"t_avg":46.472656,"t_std":30.431044,"strat_mix":{"0":3,"2":1},"representatives":[{"match_id":"adee609d-82e2-44f0-b92e-b5df529d2968","round_number":9},{"match_id":"b2ac333a-f3c5-4a46-969f-edc61aa9052a","round_number":2},{"match_id":"b2ac333a-f3c5-4a46-969f-edc61aa9052a","round_number":9}]},{"side":"CT","type":"he","cluster_id":6,"label":"Quad","det_rx":741.74115,"det_ry":842.93335,"throw_rx":907.7193,"throw_ry":797.31335,"count":3,"share":0.03628543,"t_avg":33.625,"t_std":3.5727875,"strat_mix":{"2":3},"representatives":[{"match_id":"b2ac333a-f3c5-4a46-969f-edc61aa9052a","round_number":2},{"match_id":"b2ac333a-f3c5-4a46-969f-edc61aa9052a","round_number":3},{"match_id":"b2ac333a-f3c5-4a46-969f-edc61aa9052a","round_number":5}]},{"side":"CT","type":"he","cluster_id":7,"label":"Ruins","det_rx":612.50085,"det_ry":237.49431,"throw_rx":608.49554,"throw_ry":240.76831,"count":3,"share":0.036188006,"t_avg":57.348957,"t_std":22.770714,"strat_mix":{"0":3},"representatives":[{"match_id":"adee609d-82e2-44f0-b92e-b5df529d2968","round_number":7},{"match_id":"b2ac333a-f3c5-4a46-969f-edc61aa9052a","round_number":4},{"match_id":"b2ac333a-f3c5-4a46-969f-edc61aa9052a","round_number":8}]},{"side":"CT","type":"molotov","cluster_id":0,"label":"Banana","det_rx":493.1615,"det_ry":432.214,"throw_rx":581.38196,"throw_ry":312.76163,"count":16,"share":0.22843947,"t_avg":17.942383,"t_std":10.376933,"strat_mix":{"0":8,"1":1,"2":7},"representatives":[{"match_id":"adee609d-82e2-44f0-b92e-b5df529d2968","round_number":4},{"match_id":"adee609d-82e2-44f0-b92e-b5df529d2968","round_number":5},{"match_id":"adee609d-82e2-44f0-b92e-b5df529d2968","round_number":6}]},{"side":"CT","type":"molotov","cluster_id":1,"label":"TopofMid","det_rx":653.8382,"det_ry":684.69464,"throw_rx":734.9418,"throw_ry":640.37103,"count":12,"share":0.1713296,"t_avg":17.68099,"t_std":7.3091006,"strat_mix":{"0":5,"1":1,"2":6},"representatives":[{"match_id":"adee609d-82e2-44f0-b92e-b5df529d2968","round_number":4},{"match_id":"adee609d-82e2-44f0-b92e-b5df529d2968","round_number":5},{"match_id":"adee609d-82e2-44f0-b92e-b5df529d2968","round_number":6}]},{"side":"CT","type":"molotov","cluster_id":2,"label":"TRamp","det_rx":417.24353,"det_ry":508.89444,"throw_rx":596.05035,"throw_ry":317.4837,"count":7,"share":0.1,"t_avg":16.066965,"t_std":3.4162564,"strat_mix":{"2":7},"representatives":[{"match_id":"adee609d-82e2-44f0-b92e-b5df529d2968","round_number":5},{"match_id":"adee609d-82e2-44f0-b92e-b5df529d2968","round_number":8},{"match_id":"adee609d-82e2-44f0-b92e-b5df529d2968","round_number":11}]},{"side":"CT","type":"molotov","cluster_id":3,"label":"Balcony","det_rx":797.6559,"det_ry":854.54395,"throw_rx":882.238,"throw_ry":778.3504,"count":6,"share":0.08578026,"t_avg":36.726562,"t_std":19.740274,"strat_mix":{"0":1,"2":5},"representatives":[{"match_id":"adee609d-82e2-44f0-b92e-b5df529d2968","round_number":8},{"match_id":"adee609d-82e2-44f0-b92e-b5df529d2968","round_number":10},{"match_id":"b2ac333a-f3c5-4a46-969f-edc61aa9052a","round_number":2}]},{"side":"CT","type":"molotov","cluster_id":4,"label":"Banana","det_rx":536.5001,"det_ry":376.69388,"throw_rx":556.16644,"throw_ry":261.79727,"count":6,"share":0.08578026,"t_avg":33.885418,"t_std":7.832473,"strat_mix":{"0":5,"2":1},"representatives":[{"match_id":"adee609d-82e2-44f0-b92e-b5df529d2968","round_number":10},{"match_id":"adee609d-82e2-44f0-b92e-b5df529d2968","round_number":11},{"match_id":"b2ac333a-f3c5-4a46-969f-edc61aa9052a","round_number":4}]},{"side":"CT","type":"molotov","cluster_id":5,"label":"BombsiteB","det_rx":551.4852,"det_ry":219.31215,"throw_rx":764.06226,"throw_ry":222.20924,"count":4,"share":0.057340797,"t_avg":75.41016,"t_std":20.234587,"strat_mix":{"0":4},"representatives":[{"match_id":"b2ac333a-f3c5-4a46-969f-edc61aa9052a","round_number":4},{"match_id":"b2ac333a-f3c5-4a46-969f-edc61aa9052a","round_number":8},{"match_id":"b2ac333a-f3c5-4a46-969f-edc61aa9052a","round_number":9}]},{"side":"CT","type":"molotov","cluster_id":6,"label":"Apartments","det_rx":676.8188,"det_ry":861.5598,"throw_rx":813.5903,"throw_ry":844.10345,"count":4,"share":0.057109866,"t_avg":21.203125,"t_std":2.8894212,"strat_mix":{"0":1,"2":3},"representatives":[{"match_id":"adee609d-82e2-44f0-b92e-b5df529d2968","round_number":8},{"match_id":"adee609d-82e2-44f0-b92e-b5df529d2968","round_number":11},{"match_id":"b2ac333a-f3c5-4a46-969f-edc61aa9052a","round_number":10}]},{"side":"CT","type":"molotov","cluster_id":7,"label":"Apartments","det_rx":629.0264,"det_ry":806.9057,"throw_rx":687.96295,"throw_ry":722.25385,"count":4,"share":0.0569944,"t_avg":14.214844,"t_std":1.0890734,"strat_mix":{"0":2,"2":2},"representatives":[{"match_id":"adee609d-82e2-44f0-b92e-b5df529d2968","round_number":4},{"match_id":"adee609d-82e2-44f0-b92e-b5df529d2968","round_number":5},{"match_id":"adee609d-82e2-44f0-b92e-b5df529d2968","round_number":8}]},{"side":"CT","type":"molotov","cluster_id":8,"label":"BombsiteA","det_rx":806.7032,"det_ry":773.27704,"throw_rx":824.7799,"throw_ry":775.703,"count":3,"share":0.04289013,"t_avg":41.395832,"t_std":8.407754,"strat_mix":{"0":1,"1":1,"2":1},"representatives":[{"match_id":"adee609d-82e2-44f0-b92e-b5df529d2968","round_number":3},{"match_id":"b2ac333a-f3c5-4a46-969f-edc61aa9052a","round_number":6},{"match_id":"b2ac333a-f3c5-4a46-969f-edc61aa9052a","round_number":11}]},{"side":"CT","type":"smoke","cluster_id":0,"label":"BombsiteB","det_rx":589.6388,"det_ry":323.66672,"throw_rx":551.7172,"throw_ry":212.65462,"count":19,"share":0.21581091,"t_avg":54.15872,"t_std":16.698072,"strat_mix":{"0":12,"1":3,"2":4},"representatives":[{"match_id":"adee609d-82e2-44f0-b92e-b5df529d2968","round_number":2},{"match_id":"adee609d-82e2-44f0-b92e-b5df529d2968","round_number":3},{"match_id":"adee609d-82e2-44f0-b92e-b5df529d2968","round_number":4}]},{"side":"CT","type":"smoke","cluster_id":1,"label":"Balcony","det_rx":808.76764,"det_ry":839.5519,"throw_rx":880.61646,"throw_ry":773.891,"count":15,"share":0.17043993,"t_avg":49.62604,"t_std":14.132084,"strat_mix":{"0":6,"1":3,"2":6},"representatives":[{"match_id":"adee609d-82e2-44f0-b92e-b5df529d2968","round_number":2},{"match_id":"adee609d-82e2-44f0-b92e-b5df529d2968","round_number":2},{"match_id":"adee609d-82e2-44f0-b92e-b5df529d2968","round_number":3}]},{"side":"CT","type":"smoke","cluster_id":2,"label":"TRamp","det_rx":454.2495,"det_ry":587.31036,"throw_rx":741.9944,"throw_ry":389.0692,"count":12,"share":0.13666445,"t_avg":12.145833,"t_std":12.517264,"strat_mix":{"0":1,"1":1,"2":10},"representatives":[{"match_id":"adee609d-82e2-44f0-b92e-b5df529d2968","round_number":8},{"match_id":"adee609d-82e2-44f0-b92e-b5df529d2968","round_number":8},{"match_id":"adee609d-82e2-44f0-b92e-b5df529d2968","round_number":11}]},{"side":"CT","type":"smoke","cluster_id":3,"label":"Banana","det_rx":502.95456,"det_ry":423.69675,"throw_rx":678.16705,"throw_ry":299.5935,"count":10,"share":0.11365725,"t_avg":23.24375,"t_std":16.798124,"strat_mix":{"0":7,"2":3},"representatives":[{"match_id":"adee609d-82e2-44f0-b92e-b5df529d2968","round_number":4},{"match_id":"adee609d-82e2-44f0-b92e-b5df529d2968","round_number":4},{"match_id":"adee609d-82e2-44f0-b92e-b5df529d2968","round_number":5}]},{"side":"CT","type":"smoke","cluster_id":4,"label":"Banana","det_rx":461.63477,"det_ry":491.00568,"throw_rx":867.0323,"throw_ry":393.78564,"count":6,"share":0.06819435,"t_avg":2.3385417,"t_std":1.4671885,"strat_mix":{"0":3,"1":2,"2":1},"representatives":[{"match_id":"adee609d-82e2-44f0-b92e-b5df529d2968","round_number":3},{"match_id":"adee609d-82e2-44f0-b92e-b5df529d2968","round_number":7},{"match_id":"adee609d-82e2-44f0-b92e-b5df529d2968","round_number":12}]},{"side":"CT","type":"smoke","cluster_id":5,"label":"TopofMid","det_rx":662.574,"det_ry":687.521,"throw_rx":703.30066,"throw_ry":703.772,"count":5,"share":0.056690753,"t_avg":44.16875,"t_std":18.718351,"strat_mix":{"0":1,"1":2,"2":2},"representatives":[{"match_id":"adee609d-82e2-44f0-b92e-b5df529d2968","round_number":2},{"match_id":"adee609d-82e2-44f0-b92e-b5df529d2968","round_number":8},{"match_id":"adee609d-82e2-44f0-b92e-b5df529d2968","round_number":8}]},{"side":"CT","type":"smoke","cluster_id":6,"label":"BombsiteA","det_rx":883.22797,"det_ry":659.73126,"throw_rx":889.5807,"throw_ry":652.26373,"count":3,"share":0.034051217,"t_avg":70.260414,"t_std":7.673305,"strat_mix":{"0":2,"2":1},"representatives":[{"match_id":"adee609d-82e2-44f0-b92e-b5df529d2968","round_number":5},{"match_id":"adee609d-82e2-44f0-b92e-b5df529d2968","round_number":6},{"match_id":"b2ac333a-f3c5-4a46-969f-edc61aa9052a","round_number":11}]},{"side":"CT","type":"smoke","cluster_id":7,"label":"Banana","det_rx":552.3469,"det_ry":387.2053,"throw_rx":589.46027,"throw_ry":278.14908,"count":3,"share":0.0339593,"t_avg":16.755209,"t_std":8.168646,"strat_mix":{"1":2,"2":1},"representatives":[{"match_id":"adee609d-82e2-44f0-b92e-b5df529d2968","round_number":2},{"match_id":"adee609d-82e2-44f0-b92e-b5df529d2968","round_number":3},{"match_id":"adee609d-82e2-44f0-b92e-b5df529d2968","round_number":11}]},{"side":"CT","type":"smoke","cluster_id":8,"label":"Underpass","det_rx":511.489,"det_ry":668.2246,"throw_rx":934.6501,"throw_ry":363.30188,"count":3,"share":0.0339593,"t_avg":0.28645834,"t_std":0.026557393,"strat_mix":{"0":3},"representatives":[{"match_id":"adee609d-82e2-44f0-b92e-b5df529d2968","round_number":6},{"match_id":"adee609d-82e2-44f0-b92e-b5df529d2968","round_number":9},{"match_id":"adee609d-82e2-44f0-b92e-b5df529d2968","round_number":10}]},{"side":"T","type":"flash","cluster_id":0,"label":"Banana","det_rx":516.8129,"det_ry":402.96112,"throw_rx":459.56287,"throw_ry":565.8064,"count":12,"share":0.1997029,"t_avg":20.453125,"t_std":27.125473,"strat_mix":{"0":2,"1":1,"2":9},"representatives":[{"match_id":"adee609d-82e2-44f0-b92e-b5df529d2968","round_number":14},{"match_id":"adee609d-82e2-44f0-b92e-b5df529d2968","round_number":15},{"match_id":"adee609d-82e2-44f0-b92e-b5df529d2968","round_number":16}]},{"side":"T","type":"flash","cluster_id":1,"label":"Middle","det_rx":587.96375,"det_ry":670.72284,"throw_rx":375.1302,"throw_ry":611.1514,"count":7,"share":0.116684675,"t_avg":7.872768,"t_std":1.1985048,"strat_mix":{"0":2,"2":5},"representatives":[{"match_id":"adee609d-82e2-44f0-b92e-b5df529d2968","round_number":15},{"match_id":"adee609d-82e2-44f0-b92e-b5df529d2968","round_number":16},{"match_id":"adee609d-82e2-44f0-b92e-b5df529d2968","round_number":18}]},{"side":"T","type":"flash","cluster_id":2,"label":"BombsiteB","det_rx":572.83405,"det_ry":282.5879,"throw_rx":503.43457,"throw_ry":446.54944,"count":7,"share":0.116684675,"t_avg":40.975445,"t_std":24.840326,"strat_mix":{"0":1,"2":6},"representatives":[{"match_id":"adee609d-82e2-44f0-b92e-b5df529d2968","round_number":16},{"match_id":"adee609d-82e2-44f0-b92e-b5df529d2968","round_number":17},{"match_id":"adee609d-82e2-44f0-b92e-b5df529d2968","round_number":18}]},{"side":"T","type":"flash","cluster_id":3,"label":"Arch","det_rx":737.74316,"det_ry":586.68225,"throw_rx":625.0761,"throw_ry":706.51807,"count":7,"share":0.11641459,"t_avg":46.638393,"t_std":6.2781534,"strat_mix":{"0":5,"2":2},"representatives":[{"match_id":"adee609d-82e2-44f0-b92e-b5df529d2968","round_number":15},{"match_id":"adee609d-82e2-44f0-b92e-b5df529d2968","round_number":17},{"match_id":"adee609d-82e2-44f0-b92e-b5df529d2968","round_number":22}]},{"side":"T","type":"flash","cluster_id":4,"label":"TRamp","det_rx":440.08615,"det_ry":540.0198,"throw_rx":385.55658,"throw_ry":643.4109,"count":6,"share":0.10018906,"t_avg":13.723958,"t_std":5.9664497,"strat_mix":{"2":6},"representatives":[{"match_id":"adee609d-82e2-44f0-b92e-b5df529d2968","round_number":18},{"match_id":"adee609d-82e2-44f0-b92e-b5df529d2968","round_number":18},{"match_id":"adee609d-82e2-44f0-b92e-b5df529d2968","round_number":21}]},{"side":"T","type":"flash","cluster_id":5,"label":"Apartments","det_rx":676.63293,"det_ry":812.467,"throw_rx":566.2645,"throw_ry":807.3121,"count":4,"share":0.06665766,"t_avg":25.324219,"t_std":2.7229533,"strat_mix":{"0":2,"2":2},"representatives":[{"match_id":"adee609d-82e2-44f0-b92e-b5df529d2968","round_number":15},{"match_id":"adee609d-82e2-44f0-b92e-b5df529d2968","round_number":19},{"match_id":"adee609d-82e2-44f0-b92e-b5df529d2968","round_number":20}]},{"side":"T","type":"flash","cluster_id":6,"label":"Quad","det_rx":710.6815,"det_ry":754.4514,"throw_rx":595.7009,"throw_ry":677.1918,"count":4,"share":0.06665766,"t_avg":36.464844,"t_std":5.960404,"strat_mix":{"1":1,"2":3},"representatives":[{"match_id":"adee609d-82e2-44f0-b92e-b5df529d2968","round_number":16},{"match_id":"adee609d-82e2-44f0-b92e-b5df529d2968","round_number":16},{"match_id":"adee609d-82e2-44f0-b92e-b5df529d2968","round_number":24}]},{"side":"T","type":"flash","cluster_id":7,"label":"Ruins","det_rx":641.1077,"det_ry":226.6635,"throw_rx":460.1668,"throw_ry":473.71515,"count":3,"share":0.05002701,"t_avg":28.286459,"t_std":10.814445,"strat_mix":{"2":3},"representatives":[{"match_id":"adee609d-82e2-44f0-b92e-b5df529d2968","round_number":13},{"match_id":"adee609d-82e2-44f0-b92e-b5df529d2968","round_number":21},{"match_id":"b2ac333a-f3c5-4a46-969f-edc61aa9052a","round_number":15}]},{"side":"T","type":"flash","cluster_id":8,"label":"TopofMid","det_rx":686.55347,"det_ry":693.71094,"throw_rx":439.1129,"throw_ry":646.0904,"count":3,"share":0.05002701,"t_avg":21.130209,"t_std":14.960562,"strat_mix":{"0":1,"2":2},"representatives":[{"match_id":"adee609d-82e2-44f0-b92e-b5df529d2968","round_number":20},{"match_id":"adee609d-82e2-44f0-b92e-b5df529d2968","round_number":21},{"match_id":"b2ac333a-f3c5-4a46-969f-edc61aa9052a","round_number":16}]},{"side":"T","type":"he","cluster_id":0,"label":"BombsiteB","det_rx":585.72205,"det_ry":325.38486,"throw_rx":448.81537,"throw_ry":501.44208,"count":10,"share":0.21333493,"t_avg":18.279688,"t_std":4.9073467,"strat_mix":{"0":2,"2":8},"representatives":[{"match_id":"adee609d-82e2-44f0-b92e-b5df529d2968","round_number":15},{"match_id":"adee609d-82e2-44f0-b92e-b5df529d2968","round_number":16},{"match_id":"adee609d-82e2-44f0-b92e-b5df529d2968","round_number":18}]},{"side":"T","type":"he","cluster_id":1,"label":"Quad","det_rx":687.853,"det_ry":753.4406,"throw_rx":570.9499,"throw_ry":770.29266,"count":10,"share":0.21264482,"t_avg":21.60625,"t_std":14.59381,"strat_mix":{"0":6,"1":1,"2":3},"representatives":[{"match_id":"adee609d-82e2-44f0-b92e-b5df529d2968","round_number":14},{"match_id":"adee609d-82e2-44f0-b92e-b5df529d2968","round_number":15},{"match_id":"adee609d-82e2-44f0-b92e-b5df529d2968","round_number":15}]},{"side":"T","type":"he","cluster_id":2,"label":"Banana","det_rx":515.3557,"det_ry":396.41373,"throw_rx":459.0901,"throw_ry":573.00555,"count":9,"share":0.19139759,"t_avg":23.51389,"t_std":30.18343,"strat_mix":{"0":2,"2":7},"representatives":[{"match_id":"adee609d-82e2-44f0-b92e-b5df529d2968","round_number":16},{"match_id":"adee609d-82e2-44f0-b92e-b5df529d2968","round_number":17},{"match_id":"adee609d-82e2-44f0-b92e-b5df529d2968","round_number":17}]},{"side":"T","type":"he","cluster_id":3,"label":"Banana","det_rx":588.5916,"det_ry":396.8818,"throw_rx":445.76938,"throw_ry":508.31827,"count":6,"share":0.12765591,"t_avg":19.96875,"t_std":10.365819,"strat_mix":{"0":1,"2":5},"representatives":[{"match_id":"adee609d-82e2-44f0-b92e-b5df529d2968","round_number":16},{"match_id":"adee609d-82e2-44f0-b92e-b5df529d2968","round_number":17},{"match_id":"adee609d-82e2-44f0-b92e-b5df529d2968","round_number":18}]},{"side":"T","type":"he","cluster_id":4,"label":"Underpass","det_rx":498.1751,"det_ry":667.0907,"throw_rx":415.92334,"throw_ry":580.86664,"count":3,"share":0.063741684,"t_avg":33.609375,"t_std":33.7207,"strat_mix":{"1":1,"2":2},"representatives":[{"match_id":"adee609d-82e2-44f0-b92e-b5df529d2968","round_number":19},{"match_id":"adee609d-82e2-44f0-b92e-b5df529d2968","round_number":19},{"match_id":"adee609d-82e2-44f0-b92e-b5df529d2968","round_number":23}]},{"side":"T","type":"molotov","cluster_id":0,"label":"Apartments","det_rx":671.09296,"det_ry":788.9083,"throw_rx":411.70166,"throw_ry":820.148,"count":11,"share":0.21161945,"t_avg":10.276989,"t_std":4.796822,"strat_mix":{"0":3,"1":1,"2":7},"representatives":[{"match_id":"adee609d-82e2-44f0-b92e-b5df529d2968","round_number":14},{"match_id":"adee609d-82e2-44f0-b92e-b5df529d2968","round_number":15},{"match_id":"adee609d-82e2-44f0-b92e-b5df529d2968","round_number":18}]},{"side":"T","type":"molotov","cluster_id":1,"label":"Banana","det_rx":524.3994,"det_ry":384.4639,"throw_rx":452.07028,"throw_ry":579.45355,"count":10,"share":0.19240968,"t_avg":13.321875,"t_std":9.58202,"strat_mix":{"0":2,"2":8},"representatives":[{"match_id":"adee609d-82e2-44f0-b92e-b5df529d2968","round_number":13},{"match_id":"adee609d-82e2-44f0-b92e-b5df529d2968","round_number":16},{"match_id":"adee609d-82e2-44f0-b92e-b5df529d2968","round_number":17}]},{"side":"T","type":"molotov","cluster_id":2,"label":"Banana","det_rx":597.20184,"det_ry":401.06866,"throw_rx":447.36066,"throw_ry":501.0215,"count":7,"share":0.13478036,"t_avg":17.506697,"t_std":2.8399806,"strat_mix":{"0":2,"2":5},"representatives":[{"match_id":"adee609d-82e2-44f0-b92e-b5df529d2968","round_number":15},{"match_id":"adee609d-82e2-44f0-b92e-b5df529d2968","round_number":18},{"match_id":"adee609d-82e2-44f0-b92e-b5df529d2968","round_number":21}]},{"side":"T","type":"molotov","cluster_id":3,"label":"BombsiteB","det_rx":594.28314,"det_ry":326.05347,"throw_rx":446.72546,"throw_ry":495.34518,"count":6,"share":0.11525863,"t_avg":20.536459,"t_std":9.026729,"strat_mix":{"0":2,"2":4},"representatives":[{"match_id":"adee609d-82e2-44f0-b92e-b5df529d2968","round_number":14},{"match_id":"adee609d-82e2-44f0-b92e-b5df529d2968","round_number":15},{"match_id":"adee609d-82e2-44f0-b92e-b5df529d2968","round_number":16}]},{"side":"T","type":"molotov","cluster_id":4,"label":"BombsiteB","det_rx":544.39496,"det_ry":77.721596,"throw_rx":581.4645,"throw_ry":243.82419,"count":3,"share":0.0577853,"t_avg":78.53125,"t_std":15.319232,"strat_mix":{"0":1,"2":2},"representatives":[{"match_id":"adee609d-82e2-44f0-b92e-b5df529d2968","round_number":16},{"match_id":"adee609d-82e2-44f0-b92e-b5df529d2968","round_number":17},{"match_id":"b2ac333a-f3c5-4a46-969f-edc61aa9052a","round_number":16}]},{"side":"T","type":"smoke","cluster_id":0,"label":"Ruins","det_rx":636.0764,"det_ry":237.824,"throw_rx":537.6159,"throw_ry":350.34415,"count":13,"share":0.24544738,"t_avg":41.453125,"t_std":17.385498,"strat_mix":{"1":1,"2":12},"representatives":[{"match_id":"adee609d-82e2-44f0-b92e-b5df529d2968","round_number":13},{"match_id":"adee609d-82e2-44f0-b92e-b5df529d2968","round_number":14},{"match_id":"adee609d-82e2-44f0-b92e-b5df529d2968","round_number":16}]},{"side":"T","type":"smoke","cluster_id":1,"label":"BombsiteB","det_rx":518.2114,"det_ry":132.49791,"throw_rx":547.9042,"throw_ry":314.852,"count":8,"share":0.15087995,"t_avg":43.089844,"t_std":18.866903,"strat_mix":{"0":1,"2":7},"representatives":[{"match_id":"adee609d-82e2-44f0-b92e-b5df529d2968","round_number":13},{"match_id":"adee609d-82e2-44f0-b92e-b5df529d2968","round_number":17},{"match_id":"adee609d-82e2-44f0-b92e-b5df529d2968","round_number":18}]},{"side":"T","type":"smoke","cluster_id":2,"label":"Library","det_rx":962.87067,"det_ry":563.6725,"throw_rx":540.30084,"throw_ry":663.6337,"count":4,"share":0.075439975,"t_avg":46.95703,"t_std":12.815136,"strat_mix":{"0":2,"2":2},"representatives":[{"match_id":"adee609d-82e2-44f0-b92e-b5df529d2968","round_number":15},{"match_id":"adee609d-82e2-44f0-b92e-b5df529d2968","round_number":17},{"match_id":"adee609d-82e2-44f0-b92e-b5df529d2968","round_number":24}]},{"side":"T","type":"smoke","cluster_id":3,"label":"Arch","det_rx":723.82556,"det_ry":572.9317,"throw_rx":536.7402,"throw_ry":795.14435,"count":4,"share":0.075439975,"t_avg":19.625,"t_std":3.8208318,"strat_mix":{"0":1,"2":3},"representatives":[{"match_id":"adee609d-82e2-44f0-b92e-b5df529d2968","round_number":16},{"match_id":"adee609d-82e2-44f0-b92e-b5df529d2968","round_number":17},{"match_id":"adee609d-82e2-44f0-b92e-b5df529d2968","round_number":19}]},{"side":"T","type":"smoke","cluster_id":4,"label":"BombsiteB","det_rx":587.0868,"det_ry":321.96356,"throw_rx":409.2988,"throw_ry":473.3627,"count":4,"share":0.075439975,"t_avg":39.507812,"t_std":33.822956,"strat_mix":{"2":4},"representatives":[{"match_id":"adee609d-82e2-44f0-b92e-b5df529d2968","round_number":16},{"match_id":"adee609d-82e2-44f0-b92e-b5df529d2968","round_number":18},{"match_id":"adee609d-82e2-44f0-b92e-b5df529d2968","round_number":24}]},{"side":"T","type":"smoke","cluster_id":5,"label":"Banana","det_rx":470.8182,"det_ry":440.41287,"throw_rx":503.45444,"throw_ry":495.88495,"count":3,"share":0.05692386,"t_avg":21.255209,"t_std":16.503119,"strat_mix":{"2":3},"representatives":[{"match_id":"b2ac333a-f3c5-4a46-969f-edc61aa9052a","round_number":15},{"match_id":"b2ac333a-f3c5-4a46-969f-edc61aa9052a","round_number":16},{"match_id":"b2ac333a-f3c5-4a46-969f-edc61aa9052a","round_number":18}]},{"side":"T","type":"smoke","cluster_id":6,"label":"Arch","det_rx":807.92053,"det_ry":516.47253,"throw_rx":467.95132,"throw_ry":700.65674,"count":3,"share":0.05661819,"t_avg":39.630207,"t_std":2.0593543,"strat_mix":{"0":1,"2":2},"representatives":[{"match_id":"adee609d-82e2-44f0-b92e-b5df529d2968","round_number":15},{"match_id":"adee609d-82e2-44f0-b92e-b5df529d2968","round_number":24},{"match_id":"b2ac333a-f3c5-4a46-969f-edc61aa9052a","round_number":16}]},{"side":"T","type":"smoke","cluster_id":7,"label":"Library","det_rx":895.394,"det_ry":567.9021,"throw_rx":569.51996,"throw_ry":637.9148,"count":3,"share":0.056465358,"t_avg":52.895832,"t_std":10.239517,"strat_mix":{"0":2,"2":1},"representatives":[{"match_id":"adee609d-82e2-44f0-b92e-b5df529d2968","round_number":17},{"match_id":"adee609d-82e2-44f0-b92e-b5df529d2968","round_number":22},{"match_id":"adee609d-82e2-44f0-b92e-b5df529d2968","round_number":24}]}]}
