{"boosts":[],"conditional":[{"side":"CT","buy_type":"eco","cluster_id":2,"label":null,"top_places":[{"place":"BombsiteB","weight":0.319},{"place":"CTSideUpper","weight":0.153},{"place":"Middle","weight":0.118},{"place":"BombsiteA","weight":0.062},{"place":"Walkway","weight":0.055}],"prob":0.3724545954870666,"sample_size":6},{"side":"CT","buy_type":"force","cluster_id":4,"label":null,"top_places":[{"place":"CTSideUpper","weight":0.16},{"place":"Middle","weight":0.121},{"place":"BombsiteB","weight":0.109},{"place":"BombsiteA","weight":0.094},{"place":"Main","weight":0.068}],"prob":0.34198750927233135,"sample_size":13},{"side":"CT","buy_type":"full","cluster_id":0,"label":null,"top_places":[{"place":"BombsiteB","weight":0.222},{"place":"Middle","weight":0.188},{"place":"CTSideUpper","weight":0.151},{"place":"Main","weight":0.064},{"place":"Walkway","weight":0.058}],"prob":0.6169510181618052,"sample_size":60},{"side":"CT","buy_type":"pistol","cluster_id":4,"label":null,"top_places":[{"place":"CTSideUpper","weight":0.16},{"place":"Middle","weight":0.121},{"place":"BombsiteB","weight":0.109},{"place":"BombsiteA","weight":0.094},{"place":"Main","weight":0.068}],"prob":0.29328563566318105,"sample_size":10},{"side":"CT","buy_type":"semi","cluster_id":4,"label":null,"top_places":[{"place":"CTSideUpper","weight":0.16},{"place":"Middle","weight":0.121},{"place":"BombsiteB","weight":0.109},{"place":"BombsiteA","weight":0.094},{"place":"Main","weight":0.068}],"prob":0.297362516404894,"sample_size":3},{"side":"T","buy_type":"eco","cluster_id":0,"label":null,"top_places":[{"place":"Ruins","weight":0.177},{"place":"Bridge","weight":0.169},{"place":"Street","weight":0.168},{"place":"TSideUpper","weight":0.094},{"place":"Canal","weight":0.05}],"prob":0.5113740598055403,"sample_size":8},{"side":"T","buy_type":"force","cluster_id":0,"label":null,"top_places":[{"place":"Ruins","weight":0.177},{"place":"Bridge","weight":0.169},{"place":"Street","weight":0.168},{"place":"TSideUpper","weight":0.094},{"place":"Canal","weight":0.05}],"prob":0.5102366538249863,"sample_size":10},{"side":"T","buy_type":"full","cluster_id":0,"label":null,"top_places":[{"place":"Ruins","weight":0.177},{"place":"Bridge","weight":0.169},{"place":"Street","weight":0.168},{"place":"TSideUpper","weight":0.094},{"place":"Canal","weight":0.05}],"prob":0.4948198785350829,"sample_size":47},{"side":"T","buy_type":"pistol","cluster_id":0,"label":null,"top_places":[{"place":"Ruins","weight":0.177},{"place":"Bridge","weight":0.169},{"place":"Street","weight":0.168},{"place":"TSideUpper","weight":0.094},{"place":"Canal","weight":0.05}],"prob":0.48263135744116026,"sample_size":7},{"side":"T","buy_type":"semi","cluster_id":0,"label":null,"top_places":[{"place":"Ruins","weight":0.177},{"place":"Bridge","weight":0.169},{"place":"Street","weight":0.168},{"place":"TSideUpper","weight":0.094},{"place":"Canal","weight":0.05}],"prob":0.5146237911785517,"sample_size":4}],"economy":{"after_pistol_loss":{"eco":4,"force":5,"semi":1},"buy_CT":{"eco":6,"force":13,"full":60,"semi":3},"buy_T":{"eco":8,"force":10,"full":47,"semi":4}},"exec_templates":[],"flash_sync":[{"side":"T","kills":252,"blind_kills":17,"med_gap":0.875,"good_flashes":124,"converted":26},{"side":"CT","kills":318,"blind_kills":30,"med_gap":0.921875,"good_flashes":87,"converted":18}],"map":"de_anubis","overview":{"matches":9,"wins":6,"t_rounds":76,"t_wins":41,"ct_rounds":89,"ct_wins":45,"pistol_rounds":15,"pistol_wins":5,"conv_after_pistol_win_n":5,"conv_after_pistol_win":0.8},"playbook":{"rush_n":24,"rush_total":76,"setstrat_rounds":0,"t_rounds_all":76},"players":[{"nickname":"chopper","player_id":"a6b90eb5-aa35-55e3-b1b0-5b0e79cfa343","side":"CT","map_name":"","rounds":838,"entry_attempt_share":0.16587113,"entry_success":0.4532374,"opening_kills":63,"opening_deaths":76,"lurk_dist_avg":792.1852,"anchor_place":"BombsiteB (mirage)","anchor_share":0.29433337,"awp_round_share":0.0323741,"util_per_round":2.680191,"flash_assists_pr":0,"adr":80.249405,"tags":[]},{"nickname":"chopper","player_id":"a6b90eb5-aa35-55e3-b1b0-5b0e79cfa343","side":"T","map_name":"","rounds":834,"entry_attempt_share":0.17985612,"entry_success":0.36666667,"opening_kills":55,"opening_deaths":95,"lurk_dist_avg":624.4408,"anchor_place":"Underpass (mirage)","anchor_share":0.15744694,"awp_round_share":0.043373495,"util_per_round":3.0491607,"flash_assists_pr":0,"adr":65.41727,"tags":[]},{"nickname":"Coach|maddened","player_id":"7e68ccaf-f87f-5cd5-8e3d-9d9c5fecd8ae","side":"CT","map_name":"de_anubis","rounds":38,"entry_attempt_share":0,"entry_success":null,"opening_kills":0,"opening_deaths":0,"lurk_dist_avg":null,"anchor_place":null,"anchor_share":null,"awp_round_share":0,"util_per_round":0,"flash_assists_pr":0,"adr":0,"tags":[]},{"nickname":"Coach|maddened","player_id":"7e68ccaf-f87f-5cd5-8e3d-9d9c5fecd8ae","side":"T","map_name":"","rounds":70,"entry_attempt_share":0,"entry_success":null,"opening_kills":0,"opening_deaths":0,"lurk_dist_avg":null,"anchor_place":null,"anchor_share":null,"awp_round_share":0,"util_per_round":0,"flash_assists_pr":0,"adr":0,"tags":[]},{"nickname":"donk","player_id":"46e8db5d-d322-57e3-bb7d-d3ec171578ae","side":"CT","map_name":"de_anubis","rounds":80,"entry_attempt_share":0.2125,"entry_success":0.5294118,"opening_kills":9,"opening_deaths":8,"lurk_dist_avg":906.58685,"anchor_place":"BombsiteB","anchor_share":0.42797163,"awp_round_share":0.0875,"util_per_round":2.15,"flash_assists_pr":0,"adr":113.775,"tags":[]},{"nickname":"donk","player_id":"46e8db5d-d322-57e3-bb7d-d3ec171578ae","side":"T","map_name":"de_anubis","rounds":71,"entry_attempt_share":0.36619717,"entry_success":0.34615386,"opening_kills":9,"opening_deaths":17,"lurk_dist_avg":724.8134,"anchor_place":"Canal","anchor_share":0.3975768,"awp_round_share":0,"util_per_round":1.3943661,"flash_assists_pr":0,"adr":111.11268,"tags":["ENTRY"]},{"nickname":"magixx","player_id":"f42ceb16-5ca3-5924-8cbe-0d4ae8a1f708","side":"CT","map_name":"de_anubis","rounds":92,"entry_attempt_share":0.18478261,"entry_success":0.5882353,"opening_kills":10,"opening_deaths":7,"lurk_dist_avg":973.4139,"anchor_place":"BombsiteB","anchor_share":0.3687074,"awp_round_share":0.18478261,"util_per_round":1.576087,"flash_assists_pr":0,"adr":67.07609,"tags":[]},{"nickname":"magixx","player_id":"f42ceb16-5ca3-5924-8cbe-0d4ae8a1f708","side":"T","map_name":"de_anubis","rounds":76,"entry_attempt_share":0.17105263,"entry_success":0.15384616,"opening_kills":2,"opening_deaths":11,"lurk_dist_avg":628.854,"anchor_place":"Bridge","anchor_share":0.24565856,"awp_round_share":0.039473683,"util_per_round":3.381579,"flash_assists_pr":0,"adr":76.01316,"tags":[]},{"nickname":"sh1ro","player_id":"0803e804-7415-56e5-bd52-aa78fa01dde3","side":"CT","map_name":"de_anubis","rounds":92,"entry_attempt_share":0.1521739,"entry_success":0.78571427,"opening_kills":11,"opening_deaths":3,"lurk_dist_avg":770.7678,"anchor_place":"BombsiteA","anchor_share":0.16091277,"awp_round_share":0.5652174,"util_per_round":0.98913044,"flash_assists_pr":0,"adr":120.73913,"tags":["AWP"]},{"nickname":"sh1ro","player_id":"0803e804-7415-56e5-bd52-aa78fa01dde3","side":"T","map_name":"de_anubis","rounds":76,"entry_attempt_share":0.09210526,"entry_success":0.85714287,"opening_kills":6,"opening_deaths":1,"lurk_dist_avg":555.8716,"anchor_place":"Canal","anchor_share":0.22593236,"awp_round_share":0.34210527,"util_per_round":2.0789473,"flash_assists_pr":0,"adr":127.13158,"tags":[]},{"nickname":"zont1x","player_id":"1db70229-fdd4-5b2f-a9d3-233344715a1c","side":"CT","map_name":"de_anubis","rounds":92,"entry_attempt_share":0.19565217,"entry_success":0.44444445,"opening_kills":8,"opening_deaths":10,"lurk_dist_avg":1005.4751,"anchor_place":"BombsiteA","anchor_share":0.28930506,"awp_round_share":0.054347824,"util_per_round":2.902174,"flash_assists_pr":0,"adr":85.358696,"tags":[]},{"nickname":"zont1x","player_id":"1db70229-fdd4-5b2f-a9d3-233344715a1c","side":"T","map_name":"de_anubis","rounds":76,"entry_attempt_share":0.17105263,"entry_success":0.3846154,"opening_kills":5,"opening_deaths":8,"lurk_dist_avg":837.4683,"anchor_place":"Canal","anchor_share":0.30300677,"awp_round_share":0.039473683,"util_per_round":2.4605262,"flash_assists_pr":0,"adr":87.81579,"tags":[]},{"nickname":"zweih","player_id":"611c5cd1-5c15-51c7-8a4e-7d4757b66c32","side":"CT","map_name":"de_anubis","rounds":12,"entry_attempt_share":0.16666667,"entry_success":0,"opening_kills":0,"opening_deaths":2,"lurk_dist_avg":902.74,"anchor_place":"BombsiteB","anchor_share":0.38170323,"awp_round_share":0,"util_per_round":2,"flash_assists_pr":0,"adr":98.333336,"tags":[]},{"nickname":"zweih","player_id":"611c5cd1-5c15-51c7-8a4e-7d4757b66c32","side":"T","map_name":"de_anubis","rounds":5,"entry_attempt_share":0.2,"entry_success":1,"opening_kills":1,"opening_deaths":0,"lurk_dist_avg":480.42996,"anchor_place":"Main","anchor_share":0.40628415,"awp_round_share":0,"util_per_round":0.2,"flash_assists_pr":0,"adr":183.6,"tags":[]}],"rotations":[{"side":"CT","pattern_id":1,"place":"Main","n_contacts":5,"rotate_rate":0.6,"med_delay_sec":1.640625,"dest_mix":{"Walkway":1,"BombsiteA":2}},{"side":"CT","pattern_id":1,"place":"Middle","n_contacts":10,"rotate_rate":0.5,"med_delay_sec":1.359375,"dest_mix":{"Main":1,"Walkway":1,"BombsiteB":1}},{"side":"CT","pattern_id":1,"place":"BombsiteB","n_contacts":10,"rotate_rate":0.4,"med_delay_sec":3,"dest_mix":{"Ruins":1,"BackofB":1,"PalaceInterior":1}},{"side":"CT","pattern_id":2,"place":"Middle","n_contacts":6,"rotate_rate":0.6666667,"med_delay_sec":2.40625,"dest_mix":{"Main":1,"Walkway":1,"TunnelStairs":1}},{"side":"CT","pattern_id":3,"place":"Middle","n_contacts":6,"rotate_rate":0.6666667,"med_delay_sec":1.78125,"dest_mix":{"Walkway":1,"BombsiteA":1,"PalaceInterior":1}},{"side":"T","pattern_id":0,"place":"OutsideLong","n_contacts":6,"rotate_rate":1,"med_delay_sec":1.546875,"dest_mix":{"Ruins":1,"BombsiteB":5}},{"side":"T","pattern_id":2,"place":"Canal","n_contacts":6,"rotate_rate":0.6666667,"med_delay_sec":3.3515625,"dest_mix":{"Main":2,"Bridge":1,"Street":1}}],"round_tendencies":[{"rclass":"3rd round","side":"T","cluster_id":0,"label":null,"top_places":[{"place":"Ruins","weight":0.177},{"place":"Bridge","weight":0.169},{"place":"Street","weight":0.168},{"place":"TSideUpper","weight":0.094},{"place":"Canal","weight":0.05}],"n":4,"total":8,"share":0.50},{"rclass":"3rd round","side":"T","cluster_id":1,"label":null,"top_places":[{"place":"Canal","weight":0.286},{"place":"Ruins","weight":0.133},{"place":"Street","weight":0.114},{"place":"TSideUpper","weight":0.067},{"place":"Bridge","weight":0.065}],"n":3,"total":8,"share":0.38},{"rclass":"after pistol","side":"T","cluster_id":0,"label":null,"top_places":[{"place":"Ruins","weight":0.177},{"place":"Bridge","weight":0.169},{"place":"Street","weight":0.168},{"place":"TSideUpper","weight":0.094},{"place":"Canal","weight":0.05}],"n":4,"total":8,"share":0.50},{"rclass":"after pistol","side":"T","cluster_id":1,"label":null,"top_places":[{"place":"Canal","weight":0.286},{"place":"Ruins","weight":0.133},{"place":"Street","weight":0.114},{"place":"TSideUpper","weight":0.067},{"place":"Bridge","weight":0.065}],"n":3,"total":8,"share":0.38},{"rclass":"mid-game","side":"T","cluster_id":0,"label":null,"top_places":[{"place":"Ruins","weight":0.177},{"place":"Bridge","weight":0.169},{"place":"Street","weight":0.168},{"place":"TSideUpper","weight":0.094},{"place":"Canal","weight":0.05}],"n":27,"total":50,"share":0.54},{"rclass":"mid-game","side":"T","cluster_id":1,"label":null,"top_places":[{"place":"Canal","weight":0.286},{"place":"Ruins","weight":0.133},{"place":"Street","weight":0.114},{"place":"TSideUpper","weight":0.067},{"place":"Bridge","weight":0.065}],"n":16,"total":50,"share":0.32},{"rclass":"overtime","side":"T","cluster_id":0,"label":null,"top_places":[{"place":"Ruins","weight":0.177},{"place":"Bridge","weight":0.169},{"place":"Street","weight":0.168},{"place":"TSideUpper","weight":0.094},{"place":"Canal","weight":0.05}],"n":3,"total":3,"share":1.00},{"rclass":"pistol","side":"T","cluster_id":0,"label":null,"top_places":[{"place":"Ruins","weight":0.177},{"place":"Bridge","weight":0.169},{"place":"Street","weight":0.168},{"place":"TSideUpper","weight":0.094},{"place":"Canal","weight":0.05}],"n":4,"total":7,"share":0.57},{"rclass":"pistol","side":"T","cluster_id":1,"label":null,"top_places":[{"place":"Canal","weight":0.286},{"place":"Ruins","weight":0.133},{"place":"Street","weight":0.114},{"place":"TSideUpper","weight":0.067},{"place":"Bridge","weight":0.065}],"n":2,"total":7,"share":0.29},{"rclass":"3rd round","side":"CT","cluster_id":0,"label":null,"top_places":[{"place":"BombsiteB","weight":0.222},{"place":"Middle","weight":0.188},{"place":"CTSideUpper","weight":0.151},{"place":"Main","weight":0.064},{"place":"Walkway","weight":0.058}],"n":7,"total":9,"share":0.78},{"rclass":"3rd round","side":"CT","cluster_id":2,"label":null,"top_places":[{"place":"BombsiteB","weight":0.319},{"place":"CTSideUpper","weight":0.153},{"place":"Middle","weight":0.118},{"place":"BombsiteA","weight":0.062},{"place":"Walkway","weight":0.055}],"n":1,"total":9,"share":0.11},{"rclass":"after pistol","side":"CT","cluster_id":2,"label":null,"top_places":[{"place":"BombsiteB","weight":0.319},{"place":"CTSideUpper","weight":0.153},{"place":"Middle","weight":0.118},{"place":"BombsiteA","weight":0.062},{"place":"Walkway","weight":0.055}],"n":5,"total":9,"share":0.56},{"rclass":"after pistol","side":"CT","cluster_id":0,"label":null,"top_places":[{"place":"BombsiteB","weight":0.222},{"place":"Middle","weight":0.188},{"place":"CTSideUpper","weight":0.151},{"place":"Main","weight":0.064},{"place":"Walkway","weight":0.058}],"n":3,"total":9,"share":0.33},{"rclass":"mid-game","side":"CT","cluster_id":0,"label":null,"top_places":[{"place":"BombsiteB","weight":0.222},{"place":"Middle","weight":0.188},{"place":"CTSideUpper","weight":0.151},{"place":"Main","weight":0.064},{"place":"Walkway","weight":0.058}],"n":31,"total":61,"share":0.51},{"rclass":"mid-game","side":"CT","cluster_id":4,"label":null,"top_places":[{"place":"CTSideUpper","weight":0.16},{"place":"Middle","weight":0.121},{"place":"BombsiteB","weight":0.109},{"place":"BombsiteA","weight":0.094},{"place":"Main","weight":0.068}],"n":11,"total":61,"share":0.18},{"rclass":"overtime","side":"CT","cluster_id":0,"label":null,"top_places":[{"place":"BombsiteB","weight":0.222},{"place":"Middle","weight":0.188},{"place":"CTSideUpper","weight":0.151},{"place":"Main","weight":0.064},{"place":"Walkway","weight":0.058}],"n":2,"total":3,"share":0.67},{"rclass":"overtime","side":"CT","cluster_id":3,"label":null,"top_places":[{"place":"Middle","weight":0.356},{"place":"CTSideUpper","weight":0.154},{"place":"BombsiteB","weight":0.15},{"place":"Connector","weight":0.041},{"place":"Walkway","weight":0.037}],"n":1,"total":3,"share":0.33},{"rclass":"pistol","side":"CT","cluster_id":4,"label":null,"top_places":[{"place":"CTSideUpper","weight":0.16},{"place":"Middle","weight":0.121},{"place":"BombsiteB","weight":0.109},{"place":"BombsiteA","weight":0.094},{"place":"Main","weight":0.068}],"n":4,"total":10,"share":0.40},{"rclass":"pistol","side":"CT","cluster_id":3,"label":null,"top_places":[{"place":"Middle","weight":0.356},{"place":"CTSideUpper","weight":0.154},{"place":"BombsiteB","weight":0.15},{"place":"Connector","weight":0.041},{"place":"Walkway","weight":0.037}],"n":4,"total":10,"share":0.40}],"setups":[{"side":"CT","t_offset":15,"pattern_id":0,"pattern":[{"n":1,"place":"BombsiteA"},{"n":2,"place":"BombsiteB"},{"n":1,"place":"Fountain"},{"n":1,"place":"Middle"}],"observed":4,"sample_size":89,"share":0.049189825,"avg_hold_sec":13,"representatives":[{"match_id":"7c4ae662-d2f9-4aab-bcab-49c8d69bddbf","round_number":13},{"match_id":"69eab253-3780-4898-8e5a-3556b2a95d87","round_number":18},{"match_id":"8d7d81b8-fe5c-4a31-a6c6-683dbb5971c4","round_number":6}]},{"side":"CT","t_offset":15,"pattern_id":1,"pattern":[{"n":2,"place":"BombsiteB"},{"n":1,"place":"Main"},{"n":2,"place":"Middle"}],"observed":5,"sample_size":89,"share":0.045359876,"avg_hold_sec":23,"representatives":[{"match_id":"8d7d81b8-fe5c-4a31-a6c6-683dbb5971c4","round_number":12},{"match_id":"8d7d81b8-fe5c-4a31-a6c6-683dbb5971c4","round_number":5},{"match_id":"5aeefed0-dd87-4bc6-aeb5-be29a086cf2b","round_number":17}]},{"side":"CT","t_offset":15,"pattern_id":2,"pattern":[{"n":1,"place":"BombsiteA"},{"n":1,"place":"BombsiteB"},{"n":1,"place":"Connector"},{"n":2,"place":"Middle"}],"observed":3,"sample_size":89,"share":0.041043453,"avg_hold_sec":18,"representatives":[{"match_id":"69eab253-3780-4898-8e5a-3556b2a95d87","round_number":26},{"match_id":"5aeefed0-dd87-4bc6-aeb5-be29a086cf2b","round_number":15},{"match_id":"8d7d81b8-fe5c-4a31-a6c6-683dbb5971c4","round_number":8}]},{"side":"CT","t_offset":15,"pattern_id":3,"pattern":[{"n":1,"place":"Alley"},{"n":1,"place":"BackofB"},{"n":1,"place":"Main"},{"n":2,"place":"Middle"}],"observed":3,"sample_size":89,"share":0.03658248,"avg_hold_sec":11,"representatives":[{"match_id":"7c4ae662-d2f9-4aab-bcab-49c8d69bddbf","round_number":15},{"match_id":"d6284f93-fab2-49fe-b784-e6b1459a8a77","round_number":9},{"match_id":"4f7a6e3b-4ca2-4580-a0d2-8b199290228b","round_number":4}]},{"side":"T","t_offset":15,"pattern_id":0,"pattern":[{"n":3,"place":"OutsideLong"},{"n":1,"place":"Ruins"},{"n":1,"place":"Street"}],"observed":3,"sample_size":76,"share":0.052155443,"avg_hold_sec":8,"representatives":[{"match_id":"7c4ae662-d2f9-4aab-bcab-49c8d69bddbf","round_number":2},{"match_id":"7c4ae662-d2f9-4aab-bcab-49c8d69bddbf","round_number":7},{"match_id":"7c4ae662-d2f9-4aab-bcab-49c8d69bddbf","round_number":3}]},{"side":"T","t_offset":15,"pattern_id":1,"pattern":[{"n":2,"place":"Ruins"},{"n":1,"place":"Street"},{"n":2,"place":"TSideUpper"}],"observed":3,"sample_size":76,"share":0.042947493,"avg_hold_sec":7,"representatives":[{"match_id":"5aeefed0-dd87-4bc6-aeb5-be29a086cf2b","round_number":7},{"match_id":"0fc0d9a2-b14b-4670-86de-0074af3e9b70","round_number":17},{"match_id":"7c4ae662-d2f9-4aab-bcab-49c8d69bddbf","round_number":9}]},{"side":"T","t_offset":15,"pattern_id":2,"pattern":[{"n":2,"place":"Canal"},{"n":1,"place":"Ruins"},{"n":1,"place":"Street"},{"n":1,"place":"TSideUpper"}],"observed":3,"sample_size":76,"share":0.0374627,"avg_hold_sec":17,"representatives":[{"match_id":"d6284f93-fab2-49fe-b784-e6b1459a8a77","round_number":15},{"match_id":"5aeefed0-dd87-4bc6-aeb5-be29a086cf2b","round_number":12},{"match_id":"4f7a6e3b-4ca2-4580-a0d2-8b199290228b","round_number":16}]},{"side":"T","t_offset":30,"pattern_id":0,"pattern":[{"n":1,"place":"Bridge"},{"n":2,"place":"Canal"},{"n":1,"place":"Ruins"},{"n":1,"place":"TStairs"}],"observed":4,"sample_size":69,"share":0.06233563,"avg_hold_sec":15.5,"representatives":[{"match_id":"5aeefed0-dd87-4bc6-aeb5-be29a086cf2b","round_number":11},{"match_id":"7c4ae662-d2f9-4aab-bcab-49c8d69bddbf","round_number":5},{"match_id":"8d7d81b8-fe5c-4a31-a6c6-683dbb5971c4","round_number":16}]},{"side":"T","t_offset":30,"pattern_id":1,"pattern":[{"n":2,"place":"Bridge"},{"n":2,"place":"Canal"},{"n":1,"place":"Ruins"}],"observed":3,"sample_size":69,"share":0.045894336,"avg_hold_sec":17,"representatives":[{"match_id":"7c4ae662-d2f9-4aab-bcab-49c8d69bddbf","round_number":10},{"match_id":"5aeefed0-dd87-4bc6-aeb5-be29a086cf2b","round_number":7},{"match_id":"0fc0d9a2-b14b-4670-86de-0074af3e9b70","round_number":9}]},{"side":"T","t_offset":30,"pattern_id":2,"pattern":[{"n":2,"place":"Canal"},{"n":1,"place":"Ruins"},{"n":2,"place":"Street"}],"observed":3,"sample_size":69,"share":0.039360408,"avg_hold_sec":7,"representatives":[{"match_id":"d6284f93-fab2-49fe-b784-e6b1459a8a77","round_number":14},{"match_id":"69eab253-3780-4898-8e5a-3556b2a95d87","round_number":30},{"match_id":"d6284f93-fab2-49fe-b784-e6b1459a8a77","round_number":15}]}],"team":"Team Spirit","team_id":"6e8fb59d-fdd2-4fca-8417-932169e049d4","tendencies":[{"side":"CT","cluster_id":0,"label":null,"top_places":[{"place":"BombsiteB","weight":0.222},{"place":"Middle","weight":0.188},{"place":"CTSideUpper","weight":0.151},{"place":"Main","weight":0.064},{"place":"Walkway","weight":0.058}],"observed":44,"sample_size":92,"prob":0.44976020127368505},{"side":"CT","cluster_id":4,"label":null,"top_places":[{"place":"CTSideUpper","weight":0.16},{"place":"Middle","weight":0.121},{"place":"BombsiteB","weight":0.109},{"place":"BombsiteA","weight":0.094},{"place":"Main","weight":0.068}],"observed":16,"sample_size":92,"prob":0.17617344130827894},{"side":"CT","cluster_id":2,"label":null,"top_places":[{"place":"BombsiteB","weight":0.319},{"place":"CTSideUpper","weight":0.153},{"place":"Middle","weight":0.118},{"place":"BombsiteA","weight":0.062},{"place":"Walkway","weight":0.055}],"observed":13,"sample_size":92,"prob":0.1510584558534476},{"side":"CT","cluster_id":3,"label":null,"top_places":[{"place":"Middle","weight":0.356},{"place":"CTSideUpper","weight":0.154},{"place":"BombsiteB","weight":0.15},{"place":"Connector","weight":0.041},{"place":"Walkway","weight":0.037}],"observed":14,"sample_size":92,"prob":0.14495046780407264},{"side":"CT","cluster_id":1,"label":null,"top_places":[{"place":"CTSideUpper","weight":0.153},{"place":"Middle","weight":0.143},{"place":"BombsiteB","weight":0.14},{"place":"Connector","weight":0.091},{"place":"Main","weight":0.081}],"observed":4,"sample_size":92,"prob":0.06814608066671908},{"side":"CT","cluster_id":5,"label":null,"top_places":[{"place":"CTSideUpper","weight":0.983}],"observed":1,"sample_size":92,"prob":0.009911353093796682},{"side":"T","cluster_id":0,"label":null,"top_places":[{"place":"Ruins","weight":0.177},{"place":"Bridge","weight":0.169},{"place":"Street","weight":0.168},{"place":"TSideUpper","weight":0.094},{"place":"Canal","weight":0.05}],"observed":42,"sample_size":76,"prob":0.5250986057604109},{"side":"T","cluster_id":1,"label":null,"top_places":[{"place":"Canal","weight":0.286},{"place":"Ruins","weight":0.133},{"place":"Street","weight":0.114},{"place":"TSideUpper","weight":0.067},{"place":"Bridge","weight":0.065}],"observed":24,"sample_size":76,"prob":0.3359933957072097},{"side":"T","cluster_id":2,"label":null,"top_places":[{"place":"OutsideLong","weight":0.313},{"place":"Ruins","weight":0.205},{"place":"BombsiteB","weight":0.079},{"place":"Canal","weight":0.064},{"place":"Street","weight":0.056}],"observed":10,"sample_size":76,"prob":0.13890799853237937}],"thrown":[{"match_id":"0fc0d9a2-b14b-4670-86de-0074af3e9b70","round_number":6,"side":"CT","peak":0.9259287},{"match_id":"cdc20fdd-6963-4252-a9bf-08f87ca40181","round_number":5,"side":"CT","peak":0.89832264},{"match_id":"5535bc94-71f3-4258-843e-8c54c19191ab","round_number":13,"side":"CT","peak":0.8900751},{"match_id":"8d7d81b8-fe5c-4a31-a6c6-683dbb5971c4","round_number":16,"side":"T","peak":0.85431427},{"match_id":"d6284f93-fab2-49fe-b784-e6b1459a8a77","round_number":16,"side":"T","peak":0.8160368},{"match_id":"8d7d81b8-fe5c-4a31-a6c6-683dbb5971c4","round_number":20,"side":"T","peak":0.8149639},{"match_id":"69eab253-3780-4898-8e5a-3556b2a95d87","round_number":6,"side":"T","peak":0.80566716},{"match_id":"d6284f93-fab2-49fe-b784-e6b1459a8a77","round_number":14,"side":"T","peak":0.80566716},{"match_id":"5aeefed0-dd87-4bc6-aeb5-be29a086cf2b","round_number":1,"side":"T","peak":0.79189074},{"match_id":"4f7a6e3b-4ca2-4580-a0d2-8b199290228b","round_number":14,"side":"T","peak":0.79189074},{"match_id":"69eab253-3780-4898-8e5a-3556b2a95d87","round_number":30,"side":"T","peak":0.78486586},{"match_id":"4f7a6e3b-4ca2-4580-a0d2-8b199290228b","round_number":15,"side":"T","peak":0.7823527},{"match_id":"69eab253-3780-4898-8e5a-3556b2a95d87","round_number":13,"side":"CT","peak":0.7816642},{"match_id":"69eab253-3780-4898-8e5a-3556b2a95d87","round_number":27,"side":"CT","peak":0.7816642},{"match_id":"69eab253-3780-4898-8e5a-3556b2a95d87","round_number":25,"side":"CT","peak":0.7811037}],"trade_pairs":[{"trader":"donk","avenged":"zont1x","n":10},{"trader":"donk","avenged":"magixx","n":8},{"trader":"magixx","avenged":"donk","n":8},{"trader":"donk","avenged":"sh1ro","n":6},{"trader":"magixx","avenged":"tN1R","n":4},{"trader":"sh1ro","avenged":"donk","n":3},{"trader":"donk","avenged":"tN1R","n":3},{"trader":"magixx","avenged":"sh1ro","n":3},{"trader":"magixx","avenged":"zweih","n":2},{"trader":"magixx","avenged":"zont1x","n":2}],"util_dmg":[{"side":"T","he_dmg":1167,"fire_dmg":1033,"he_n":129,"fire_n":210},{"side":"CT","he_dmg":1905,"fire_dmg":646,"he_n":210,"fire_n":237}],"utility":[{"side":"CT","type":"flash","cluster_id":0,"label":"MidDoors","det_rx":525.6453,"det_ry":572.94836,"throw_rx":532.16174,"throw_ry":448.89478,"count":37,"share":0.18323238,"t_avg":18.519426,"t_std":14.618452,"strat_mix":{"0":22,"1":6,"3":7},"representatives":[{"match_id":"0fc0d9a2-b14b-4670-86de-0074af3e9b70","round_number":2},{"match_id":"0fc0d9a2-b14b-4670-86de-0074af3e9b70","round_number":3},{"match_id":"0fc0d9a2-b14b-4670-86de-0074af3e9b70","round_number":4}]},{"side":"CT","type":"flash","cluster_id":1,"label":"OutsideLong","det_rx":208.11467,"det_ry":586.6319,"throw_rx":376.15155,"throw_ry":488.1328,"count":33,"share":0.1704343,"t_avg":46.72301,"t_std":25.302689,"strat_mix":{"0":24,"3":4,"4":2},"representatives":[{"match_id":"0fc0d9a2-b14b-4670-86de-0074af3e9b70","round_number":3},{"match_id":"0fc0d9a2-b14b-4670-86de-0074af3e9b70","round_number":6},{"match_id":"0fc0d9a2-b14b-4670-86de-0074af3e9b70","round_number":7}]},{"side":"CT","type":"flash","cluster_id":2,"label":"MidDoors","det_rx":531.84375,"det_ry":510.38974,"throw_rx":603.617,"throw_ry":389.53848,"count":26,"share":0.14705157,"t_avg":20.501802,"t_std":9.56708,"strat_mix":{"0":15,"3":6,"4":3},"representatives":[{"match_id":"0fc0d9a2-b14b-4670-86de-0074af3e9b70","round_number":5},{"match_id":"0fc0d9a2-b14b-4670-86de-0074af3e9b70","round_number":5},{"match_id":"0fc0d9a2-b14b-4670-86de-0074af3e9b70","round_number":8}]},{"side":"CT","type":"flash","cluster_id":3,"label":"Main","det_rx":873.3584,"det_ry":397.91833,"throw_rx":737.6535,"throw_ry":247.62782,"count":23,"share":0.10533546,"t_avg":55.101223,"t_std":18.57627,"strat_mix":{"0":15,"3":5,"4":1},"representatives":[{"match_id":"0fc0d9a2-b14b-4670-86de-0074af3e9b70","round_number":3},{"match_id":"4f7a6e3b-4ca2-4580-a0d2-8b199290228b","round_number":1},{"match_id":"4f7a6e3b-4ca2-4580-a0d2-8b199290228b","round_number":3}]},{"side":"CT","type":"flash","cluster_id":4,"label":"Middle","det_rx":578.43695,"det_ry":417.35245,"throw_rx":700.10364,"throw_ry":341.01697,"count":14,"share":0.06833841,"t_avg":50.492188,"t_std":19.029697,"strat_mix":{"0":10,"3":2,"4":1},"representatives":[{"match_id":"4f7a6e3b-4ca2-4580-a0d2-8b199290228b","round_number":7},{"match_id":"5535bc94-71f3-4258-843e-8c54c19191ab","round_number":5},{"match_id":"5535bc94-71f3-4258-843e-8c54c19191ab","round_number":5}]},{"side":"CT","type":"flash","cluster_id":5,"label":"Canal","det_rx":685.79944,"det_ry":494.95096,"throw_rx":714.8786,"throw_ry":357.88263,"count":9,"share":0.050076183,"t_avg":11.024305,"t_std":1.3001467,"strat_mix":{"1":4,"3":2,"4":2},"representatives":[{"match_id":"4f7a6e3b-4ca2-4580-a0d2-8b199290228b","round_number":12},{"match_id":"69eab253-3780-4898-8e5a-3556b2a95d87","round_number":13},{"match_id":"69eab253-3780-4898-8e5a-3556b2a95d87","round_number":25}]},{"side":"CT","type":"flash","cluster_id":6,"label":"Connector","det_rx":373.0057,"det_ry":556.9186,"throw_rx":387.4067,"throw_ry":509.65024,"count":11,"share":0.043167606,"t_avg":66.4375,"t_std":22.916876,"strat_mix":{"0":4,"2":3,"3":3},"representatives":[{"match_id":"0fc0d9a2-b14b-4670-86de-0074af3e9b70","round_number":5},{"match_id":"0fc0d9a2-b14b-4670-86de-0074af3e9b70","round_number":7},{"match_id":"0fc0d9a2-b14b-4670-86de-0074af3e9b70","round_number":8}]},{"side":"CT","type":"flash","cluster_id":7,"label":"BombsiteA","det_rx":752.64056,"det_ry":295.46823,"throw_rx":660.4394,"throw_ry":338.72293,"count":7,"share":0.037396237,"t_avg":74.69866,"t_std":25.44134,"strat_mix":{"0":4,"2":1,"4":1},"representatives":[{"match_id":"4f7a6e3b-4ca2-4580-a0d2-8b199290228b","round_number":12},{"match_id":"69eab253-3780-4898-8e5a-3556b2a95d87","round_number":26},{"match_id":"7c4ae662-d2f9-4aab-bcab-49c8d69bddbf","round_number":17}]},{"side":"CT","type":"flash","cluster_id":8,"label":"Main","det_rx":766.29456,"det_ry":477.35193,"throw_rx":727.5511,"throw_ry":292.7088,"count":6,"share":0.03309179,"t_avg":21.205729,"t_std":14.786918,"strat_mix":{"0":3,"2":1,"4":2},"representatives":[{"match_id":"4f7a6e3b-4ca2-4580-a0d2-8b199290228b","round_number":11},{"match_id":"5535bc94-71f3-4258-843e-8c54c19191ab","round_number":3},{"match_id":"5535bc94-71f3-4258-843e-8c54c19191ab","round_number":11}]},{"side":"CT","type":"flash","cluster_id":9,"label":"BombsiteB","det_rx":285.9178,"det_ry":508.43173,"throw_rx":330.58893,"throw_ry":444.88116,"count":6,"share":0.03242573,"t_avg":78.68229,"t_std":28.446882,"strat_mix":{"0":5,"4":1},"representatives":[{"match_id":"4f7a6e3b-4ca2-4580-a0d2-8b199290228b","round_number":5},{"match_id":"5535bc94-71f3-4258-843e-8c54c19191ab","round_number":7},{"match_id":"69eab253-3780-4898-8e5a-3556b2a95d87","round_number":19}]},{"side":"CT","type":"flash","cluster_id":10,"label":"Fountain","det_rx":879.62854,"det_ry":260.16348,"throw_rx":691.84033,"throw_ry":355.8051,"count":5,"share":0.0259781,"t_avg":39.615623,"t_std":12.00458,"strat_mix":{"0":1,"2":3,"4":1},"representatives":[{"match_id":"4f7a6e3b-4ca2-4580-a0d2-8b199290228b","round_number":10},{"match_id":"4f7a6e3b-4ca2-4580-a0d2-8b199290228b","round_number":11},{"match_id":"5535bc94-71f3-4258-843e-8c54c19191ab","round_number":2}]},{"side":"CT","type":"flash","cluster_id":11,"label":"Walkway","det_rx":672.59717,"det_ry":400.2316,"throw_rx":668.3574,"throw_ry":339.87018,"count":3,"share":0.024271375,"t_avg":99.71354,"t_std":17.46303,"strat_mix":{"0":2,"4":1},"representatives":[{"match_id":"5aeefed0-dd87-4bc6-aeb5-be29a086cf2b","round_number":21},{"match_id":"69eab253-3780-4898-8e5a-3556b2a95d87","round_number":23},{"match_id":"7c4ae662-d2f9-4aab-bcab-49c8d69bddbf","round_number":17}]},{"side":"CT","type":"flash","cluster_id":12,"label":"Connector","det_rx":450.76443,"det_ry":614.2685,"throw_rx":319.64566,"throw_ry":529.6168,"count":4,"share":0.016766049,"t_avg":56.996094,"t_std":16.582596,"strat_mix":{"2":1,"3":1,"4":2},"representatives":[{"match_id":"d6284f93-fab2-49fe-b784-e6b1459a8a77","round_number":4},{"match_id":"d6284f93-fab2-49fe-b784-e6b1459a8a77","round_number":6},{"match_id":"d6284f93-fab2-49fe-b784-e6b1459a8a77","round_number":9}]},{"side":"CT","type":"flash","cluster_id":13,"label":"OutsideLong","det_rx":277.46658,"det_ry":644.52423,"throw_rx":376.48724,"throw_ry":480.77454,"count":3,"share":0.016267573,"t_avg":53.046875,"t_std":5.082058,"strat_mix":{"2":2,"4":1},"representatives":[{"match_id":"5aeefed0-dd87-4bc6-aeb5-be29a086cf2b","round_number":14},{"match_id":"d6284f93-fab2-49fe-b784-e6b1459a8a77","round_number":5},{"match_id":"d6284f93-fab2-49fe-b784-e6b1459a8a77","round_number":6}]},{"side":"CT","type":"he","cluster_id":0,"label":"Bridge","det_rx":493.50415,"det_ry":595.436,"throw_rx":441.02762,"throw_ry":507.73236,"count":71,"share":0.3845732,"t_avg":33.851894,"t_std":18.922503,"strat_mix":{"0":50,"2":5,"3":8},"representatives":[{"match_id":"0fc0d9a2-b14b-4670-86de-0074af3e9b70","round_number":3},{"match_id":"0fc0d9a2-b14b-4670-86de-0074af3e9b70","round_number":4},{"match_id":"4f7a6e3b-4ca2-4580-a0d2-8b199290228b","round_number":3}]},{"side":"CT","type":"he","cluster_id":1,"label":"Connector","det_rx":372.059,"det_ry":571.4741,"throw_rx":324.8027,"throw_ry":442.846,"count":19,"share":0.079266466,"t_avg":70.51727,"t_std":24.717405,"strat_mix":{"0":16,"3":1,"4":1},"representatives":[{"match_id":"0fc0d9a2-b14b-4670-86de-0074af3e9b70","round_number":2},{"match_id":"0fc0d9a2-b14b-4670-86de-0074af3e9b70","round_number":2},{"match_id":"0fc0d9a2-b14b-4670-86de-0074af3e9b70","round_number":5}]},{"side":"CT","type":"he","cluster_id":2,"label":"TSideUpper","det_rx":794.3847,"det_ry":553.4617,"throw_rx":681.98157,"throw_ry":387.89484,"count":15,"share":0.06564494,"t_avg":14.791667,"t_std":6.793649,"strat_mix":{"0":8,"1":3,"4":2},"representatives":[{"match_id":"4f7a6e3b-4ca2-4580-a0d2-8b199290228b","round_number":5},{"match_id":"4f7a6e3b-4ca2-4580-a0d2-8b199290228b","round_number":6},{"match_id":"4f7a6e3b-4ca2-4580-a0d2-8b199290228b","round_number":7}]},{"side":"CT","type":"he","cluster_id":3,"label":"BombsiteB","det_rx":266.7626,"det_ry":540.96265,"throw_rx":361.63098,"throw_ry":476.1895,"count":13,"share":0.056144934,"t_avg":25.877403,"t_std":20.920345,"strat_mix":{"0":11,"1":1,"3":1},"representatives":[{"match_id":"4f7a6e3b-4ca2-4580-a0d2-8b199290228b","round_number":4},{"match_id":"5535bc94-71f3-4258-843e-8c54c19191ab","round_number":7},{"match_id":"5aeefed0-dd87-4bc6-aeb5-be29a086cf2b","round_number":20}]},{"side":"CT","type":"he","cluster_id":4,"label":"Middle","det_rx":602.13586,"det_ry":399.71472,"throw_rx":707.9112,"throw_ry":352.19366,"count":11,"share":0.052200157,"t_avg":79.31875,"t_std":11.37075,"strat_mix":{"0":6,"3":3,"4":2},"representatives":[{"match_id":"4f7a6e3b-4ca2-4580-a0d2-8b199290228b","round_number":12},{"match_id":"5aeefed0-dd87-4bc6-aeb5-be29a086cf2b","round_number":19},{"match_id":"69eab253-3780-4898-8e5a-3556b2a95d87","round_number":16}]},{"side":"CT","type":"he","cluster_id":5,"label":"MidDoors","det_rx":526.8589,"det_ry":503.47678,"throw_rx":593.0818,"throw_ry":423.12662,"count":12,"share":0.04391726,"t_avg":34.235676,"t_std":13.417521,"strat_mix":{"0":10,"1":1,"3":1},"representatives":[{"match_id":"4f7a6e3b-4ca2-4580-a0d2-8b199290228b","round_number":7},{"match_id":"5535bc94-71f3-4258-843e-8c54c19191ab","round_number":5},{"match_id":"5535bc94-71f3-4258-843e-8c54c19191ab","round_number":6}]},{"side":"CT","type":"he","cluster_id":6,"label":"Main","det_rx":848.646,"det_ry":410.31686,"throw_rx":762.3393,"throw_ry":289.49365,"count":10,"share":0.039924204,"t_avg":51.1625,"t_std":23.983364,"strat_mix":{"2":3,"3":3,"4":2},"representatives":[{"match_id":"0fc0d9a2-b14b-4670-86de-0074af3e9b70","round_number":7},{"match_id":"0fc0d9a2-b14b-4670-86de-0074af3e9b70","round_number":8},{"match_id":"4f7a6e3b-4ca2-4580-a0d2-8b199290228b","round_number":10}]},{"side":"CT","type":"he","cluster_id":7,"label":"Walkway","det_rx":656.28796,"det_ry":384.88654,"throw_rx":752.26874,"throw_ry":296.1625,"count":7,"share":0.03644636,"t_avg":71.91741,"t_std":36.80934,"strat_mix":{"0":4,"1":2,"4":1},"representatives":[{"match_id":"0fc0d9a2-b14b-4670-86de-0074af3e9b70","round_number":3},{"match_id":"4f7a6e3b-4ca2-4580-a0d2-8b199290228b","round_number":8},{"match_id":"5aeefed0-dd87-4bc6-aeb5-be29a086cf2b","round_number":21}]},{"side":"CT","type":"he","cluster_id":8,"label":"Bridge","det_rx":488.59534,"det_ry":686.04205,"throw_rx":548.1359,"throw_ry":480.55048,"count":9,"share":0.03602547,"t_avg":14.145833,"t_std":11.394893,"strat_mix":{"0":6,"2":1,"3":1},"representatives":[{"match_id":"0fc0d9a2-b14b-4670-86de-0074af3e9b70","round_number":2},{"match_id":"0fc0d9a2-b14b-4670-86de-0074af3e9b70","round_number":5},{"match_id":"4f7a6e3b-4ca2-4580-a0d2-8b199290228b","round_number":2}]},{"side":"CT","type":"he","cluster_id":9,"label":"Main","det_rx":809.42926,"det_ry":471.67853,"throw_rx":851.9241,"throw_ry":310.20505,"count":7,"share":0.027558492,"t_avg":34.691963,"t_std":17.689228,"strat_mix":{"0":6,"3":1},"representatives":[{"match_id":"0fc0d9a2-b14b-4670-86de-0074af3e9b70","round_number":3},{"match_id":"5535bc94-71f3-4258-843e-8c54c19191ab","round_number":3},{"match_id":"5535bc94-71f3-4258-843e-8c54c19191ab","round_number":5}]},{"side":"CT","type":"he","cluster_id":10,"label":"BombsiteA","det_rx":754.0732,"det_ry":328.32913,"throw_rx":654.15906,"throw_ry":335.954,"count":5,"share":0.02606329,"t_avg":67.43125,"t_std":21.195065,"strat_mix":{"0":4,"3":1},"representatives":[{"match_id":"4f7a6e3b-4ca2-4580-a0d2-8b199290228b","round_number":12},{"match_id":"5535bc94-71f3-4258-843e-8c54c19191ab","round_number":10},{"match_id":"69eab253-3780-4898-8e5a-3556b2a95d87","round_number":26}]},{"side":"CT","type":"he","cluster_id":11,"label":"OutsideLong","det_rx":179.86377,"det_ry":576.1164,"throw_rx":322.79837,"throw_ry":513.18567,"count":4,"share":0.02574324,"t_avg":44.972656,"t_std":9.187927,"strat_mix":{"0":3,"4":1},"representatives":[{"match_id":"69eab253-3780-4898-8e5a-3556b2a95d87","round_number":18},{"match_id":"69eab253-3780-4898-8e5a-3556b2a95d87","round_number":18},{"match_id":"7c4ae662-d2f9-4aab-bcab-49c8d69bddbf","round_number":14}]},{"side":"CT","type":"he","cluster_id":12,"label":"Fountain","det_rx":869.7742,"det_ry":304.55505,"throw_rx":691.3078,"throw_ry":337.97983,"count":6,"share":0.024237808,"t_avg":79.125,"t_std":29.020123,"strat_mix":{"0":3,"1":2,"3":1},"representatives":[{"match_id":"5535bc94-71f3-4258-843e-8c54c19191ab","round_number":6},{"match_id":"69eab253-3780-4898-8e5a-3556b2a95d87","round_number":23},{"match_id":"8d7d81b8-fe5c-4a31-a6c6-683dbb5971c4","round_number":8}]},{"side":"CT","type":"he","cluster_id":13,"label":"OutsideLong","det_rx":227.23949,"det_ry":624.07446,"throw_rx":358.43536,"throw_ry":526.6517,"count":5,"share":0.023871437,"t_avg":41.74375,"t_std":18.948717,"strat_mix":{"0":3,"1":1,"3":1},"representatives":[{"match_id":"69eab253-3780-4898-8e5a-3556b2a95d87","round_number":24},{"match_id":"7c4ae662-d2f9-4aab-bcab-49c8d69bddbf","round_number":14},{"match_id":"8d7d81b8-fe5c-4a31-a6c6-683dbb5971c4","round_number":4}]},{"side":"CT","type":"he","cluster_id":14,"label":"TStairs","det_rx":689.0959,"det_ry":632.4459,"throw_rx":676.3446,"throw_ry":366.90146,"count":5,"share":0.021624433,"t_avg":21.6875,"t_std":11.410398,"strat_mix":{"0":3,"2":1,"4":1},"representatives":[{"match_id":"4f7a6e3b-4ca2-4580-a0d2-8b199290228b","round_number":9},{"match_id":"5535bc94-71f3-4258-843e-8c54c19191ab","round_number":13},{"match_id":"69eab253-3780-4898-8e5a-3556b2a95d87","round_number":16}]},{"side":"CT","type":"he","cluster_id":15,"label":"MidDoors","det_rx":580.1136,"det_ry":602.27264,"throw_rx":581.34894,"throw_ry":407.80658,"count":3,"share":0.018320993,"t_avg":17.385416,"t_std":4.3360305,"strat_mix":{"0":3},"representatives":[{"match_id":"5535bc94-71f3-4258-843e-8c54c19191ab","round_number":9},{"match_id":"69eab253-3780-4898-8e5a-3556b2a95d87","round_number":18},{"match_id":"69eab253-3780-4898-8e5a-3556b2a95d87","round_number":20}]},{"side":"CT","type":"he","cluster_id":16,"label":"Walkway","det_rx":730.8485,"det_ry":470.68375,"throw_rx":781.87933,"throw_ry":379.81207,"count":3,"share":0.013461375,"t_avg":21.109375,"t_std":8.220364,"strat_mix":{"0":3},"representatives":[{"match_id":"69eab253-3780-4898-8e5a-3556b2a95d87","round_number":19},{"match_id":"8d7d81b8-fe5c-4a31-a6c6-683dbb5971c4","round_number":5},{"match_id":"cdc20fdd-6963-4252-a9bf-08f87ca40181","round_number":5}]},{"side":"CT","type":"molotov","cluster_id":0,"label":"Bridge","det_rx":507.3874,"det_ry":607.76447,"throw_rx":550.4409,"throw_ry":434.59796,"count":97,"share":0.4007408,"t_avg":12.039626,"t_std":8.536933,"strat_mix":{"0":71,"1":6,"3":12},"representatives":[{"match_id":"0fc0d9a2-b14b-4670-86de-0074af3e9b70","round_number":2},{"match_id":"0fc0d9a2-b14b-4670-86de-0074af3e9b70","round_number":2},{"match_id":"0fc0d9a2-b14b-4670-86de-0074af3e9b70","round_number":3}]},{"side":"CT","type":"molotov","cluster_id":1,"label":"Main","det_rx":805.8558,"det_ry":474.95398,"throw_rx":814.4645,"throw_ry":350.15616,"count":39,"share":0.17488493,"t_avg":16.194311,"t_std":12.786977,"strat_mix":{"0":30,"3":5,"4":2},"representatives":[{"match_id":"0fc0d9a2-b14b-4670-86de-0074af3e9b70","round_number":2},{"match_id":"0fc0d9a2-b14b-4670-86de-0074af3e9b70","round_number":4},{"match_id":"0fc0d9a2-b14b-4670-86de-0074af3e9b70","round_number":8}]},{"side":"CT","type":"molotov","cluster_id":2,"label":"Bridge","det_rx":464.30283,"det_ry":610.21796,"throw_rx":359.9799,"throw_ry":556.33527,"count":36,"share":0.15143138,"t_avg":28.208767,"t_std":17.728264,"strat_mix":{"0":28,"1":2,"3":4},"representatives":[{"match_id":"4f7a6e3b-4ca2-4580-a0d2-8b199290228b","round_number":6},{"match_id":"4f7a6e3b-4ca2-4580-a0d2-8b199290228b","round_number":7},{"match_id":"5535bc94-71f3-4258-843e-8c54c19191ab","round_number":3}]},{"side":"CT","type":"molotov","cluster_id":3,"label":"Connector","det_rx":386.1267,"det_ry":566.5438,"throw_rx":310.50317,"throw_ry":484.94583,"count":15,"share":0.062586956,"t_avg":68.833336,"t_std":15.848694,"strat_mix":{"0":12,"2":1,"4":1},"representatives":[{"match_id":"4f7a6e3b-4ca2-4580-a0d2-8b199290228b","round_number":3},{"match_id":"4f7a6e3b-4ca2-4580-a0d2-8b199290228b","round_number":5},{"match_id":"5535bc94-71f3-4258-843e-8c54c19191ab","round_number":8}]},{"side":"CT","type":"molotov","cluster_id":4,"label":"Main","det_rx":833.87354,"det_ry":427.36844,"throw_rx":774.5473,"throw_ry":304.6966,"count":13,"share":0.046969518,"t_avg":44.070915,"t_std":15.892143,"strat_mix":{"0":8,"3":2,"4":2},"representatives":[{"match_id":"0fc0d9a2-b14b-4670-86de-0074af3e9b70","round_number":3},{"match_id":"0fc0d9a2-b14b-4670-86de-0074af3e9b70","round_number":5},{"match_id":"5535bc94-71f3-4258-843e-8c54c19191ab","round_number":5}]},{"side":"CT","type":"molotov","cluster_id":5,"label":"OutsideLong","det_rx":190.74791,"det_ry":597.1686,"throw_rx":350.58124,"throw_ry":481.39682,"count":7,"share":0.02263467,"t_avg":54.53348,"t_std":41.504913,"strat_mix":{"0":3,"2":1,"4":1},"representatives":[{"match_id":"0fc0d9a2-b14b-4670-86de-0074af3e9b70","round_number":6},{"match_id":"0fc0d9a2-b14b-4670-86de-0074af3e9b70","round_number":7},{"match_id":"4f7a6e3b-4ca2-4580-a0d2-8b199290228b","round_number":4}]},{"side":"CT","type":"molotov","cluster_id":6,"label":"Walkway","det_rx":647.76874,"det_ry":388.3475,"throw_rx":740.42786,"throw_ry":334.8887,"count":5,"share":0.021971237,"t_avg":57.35,"t_std":22.913101,"strat_mix":{"0":4,"1":1},"representatives":[{"match_id":"0fc0d9a2-b14b-4670-86de-0074af3e9b70","round_number":3},{"match_id":"4f7a6e3b-4ca2-4580-a0d2-8b199290228b","round_number":3},{"match_id":"4f7a6e3b-4ca2-4580-a0d2-8b199290228b","round_number":8}]},{"side":"CT","type":"molotov","cluster_id":7,"label":"Fountain","det_rx":858.05176,"det_ry":320.0283,"throw_rx":687.5114,"throw_ry":409.37558,"count":3,"share":0.018175151,"t_avg":62.973957,"t_std":18.095911,"strat_mix":{"0":2,"4":1},"representatives":[{"match_id":"4f7a6e3b-4ca2-4580-a0d2-8b199290228b","round_number":11},{"match_id":"69eab253-3780-4898-8e5a-3556b2a95d87","round_number":16},{"match_id":"69eab253-3780-4898-8e5a-3556b2a95d87","round_number":26}]},{"side":"CT","type":"molotov","cluster_id":8,"label":"MidDoors","det_rx":521.62244,"det_ry":515.3998,"throw_rx":607.8714,"throw_ry":399.43567,"count":5,"share":0.01460439,"t_avg":41.175,"t_std":3.6319625,"strat_mix":{"0":4,"3":1},"representatives":[{"match_id":"4f7a6e3b-4ca2-4580-a0d2-8b199290228b","round_number":7},{"match_id":"5535bc94-71f3-4258-843e-8c54c19191ab","round_number":13},{"match_id":"8d7d81b8-fe5c-4a31-a6c6-683dbb5971c4","round_number":2}]},{"side":"CT","type":"smoke","cluster_id":0,"label":"Bridge","det_rx":455.8393,"det_ry":617.1567,"throw_rx":363.5575,"throw_ry":558.7812,"count":74,"share":0.25609455,"t_avg":35.829815,"t_std":14.904751,"strat_mix":{"0":46,"3":10,"4":10},"representatives":[{"match_id":"0fc0d9a2-b14b-4670-86de-0074af3e9b70","round_number":3},{"match_id":"0fc0d9a2-b14b-4670-86de-0074af3e9b70","round_number":3},{"match_id":"0fc0d9a2-b14b-4670-86de-0074af3e9b70","round_number":5}]},{"side":"CT","type":"smoke","cluster_id":1,"label":"Bridge","det_rx":506.83667,"det_ry":588.75085,"throw_rx":579.67236,"throw_ry":434.4328,"count":61,"share":0.19522426,"t_avg":21.44211,"t_std":10.971567,"strat_mix":{"0":38,"2":7,"3":10},"representatives":[{"match_id":"0fc0d9a2-b14b-4670-86de-0074af3e9b70","round_number":2},{"match_id":"0fc0d9a2-b14b-4670-86de-0074af3e9b70","round_number":3},{"match_id":"0fc0d9a2-b14b-4670-86de-0074af3e9b70","round_number":4}]},{"side":"CT","type":"smoke","cluster_id":2,"label":"Main","det_rx":795.51825,"det_ry":471.03598,"throw_rx":814.7702,"throw_ry":354.73373,"count":57,"share":0.17705569,"t_avg":32.427082,"t_std":17.237722,"strat_mix":{"0":39,"3":6,"4":7},"representatives":[{"match_id":"0fc0d9a2-b14b-4670-86de-0074af3e9b70","round_number":2},{"match_id":"0fc0d9a2-b14b-4670-86de-0074af3e9b70","round_number":3},{"match_id":"0fc0d9a2-b14b-4670-86de-0074af3e9b70","round_number":3}]},{"side":"CT","type":"smoke","cluster_id":3,"label":"OutsideLong","det_rx":233.45209,"det_ry":573.2021,"throw_rx":335.34604,"throw_ry":474.8463,"count":39,"share":0.12227335,"t_avg":58.307293,"t_std":17.016432,"strat_mix":{"0":17,"2":6,"4":10},"representatives":[{"match_id":"0fc0d9a2-b14b-4670-86de-0074af3e9b70","round_number":4},{"match_id":"0fc0d9a2-b14b-4670-86de-0074af3e9b70","round_number":5},{"match_id":"0fc0d9a2-b14b-4670-86de-0074af3e9b70","round_number":6}]},{"side":"CT","type":"smoke","cluster_id":4,"label":"Main","det_rx":860.0635,"det_ry":385.54108,"throw_rx":766.7892,"throw_ry":272.54694,"count":38,"share":0.11078853,"t_avg":53.550987,"t_std":15.8938875,"strat_mix":{"0":13,"2":9,"3":10},"representatives":[{"match_id":"0fc0d9a2-b14b-4670-86de-0074af3e9b70","round_number":7},{"match_id":"0fc0d9a2-b14b-4670-86de-0074af3e9b70","round_number":8},{"match_id":"4f7a6e3b-4ca2-4580-a0d2-8b199290228b","round_number":2}]},{"side":"CT","type":"smoke","cluster_id":5,"label":"TStairs","det_rx":691.1665,"det_ry":656.1055,"throw_rx":450.08423,"throw_ry":231.3453,"count":15,"share":0.048367694,"t_avg":3.5479167,"t_std":7.943726,"strat_mix":{"0":4,"1":6,"4":4},"representatives":[{"match_id":"4f7a6e3b-4ca2-4580-a0d2-8b199290228b","round_number":5},{"match_id":"4f7a6e3b-4ca2-4580-a0d2-8b199290228b","round_number":7},{"match_id":"4f7a6e3b-4ca2-4580-a0d2-8b199290228b","round_number":12}]},{"side":"CT","type":"smoke","cluster_id":6,"label":"Walkway","det_rx":655.0183,"det_ry":392.1162,"throw_rx":713.6857,"throw_ry":300.64877,"count":12,"share":0.040598825,"t_avg":56.3763,"t_std":15.851695,"strat_mix":{"0":5,"2":4,"4":2},"representatives":[{"match_id":"4f7a6e3b-4ca2-4580-a0d2-8b199290228b","round_number":7},{"match_id":"4f7a6e3b-4ca2-4580-a0d2-8b199290228b","round_number":8},{"match_id":"5aeefed0-dd87-4bc6-aeb5-be29a086cf2b","round_number":19}]},{"side":"CT","type":"smoke","cluster_id":7,"label":"Connector","det_rx":373.0864,"det_ry":578.21313,"throw_rx":343.48904,"throw_ry":544.5197,"count":6,"share":0.014509162,"t_avg":76.40885,"t_std":9.838116,"strat_mix":{"0":3,"2":1,"4":1},"representatives":[{"match_id":"5535bc94-71f3-4258-843e-8c54c19191ab","round_number":9},{"match_id":"8d7d81b8-fe5c-4a31-a6c6-683dbb5971c4","round_number":9},{"match_id":"d6284f93-fab2-49fe-b784-e6b1459a8a77","round_number":5}]},{"side":"CT","type":"smoke","cluster_id":8,"label":"Middle","det_rx":580.0306,"det_ry":469.36774,"throw_rx":567.9095,"throw_ry":384.58398,"count":3,"share":0.010334398,"t_avg":32.161457,"t_std":8.76889,"strat_mix":{"3":2,"4":1},"representatives":[{"match_id":"0fc0d9a2-b14b-4670-86de-0074af3e9b70","round_number":8},{"match_id":"4f7a6e3b-4ca2-4580-a0d2-8b199290228b","round_number":4},{"match_id":"5aeefed0-dd87-4bc6-aeb5-be29a086cf2b","round_number":19}]},{"side":"T","type":"flash","cluster_id":0,"label":"BombsiteB","det_rx":257.89532,"det_ry":552.3972,"throw_rx":305.78195,"throw_ry":724.0719,"count":47,"share":0.16689597,"t_avg":29.86669,"t_std":28.449112,"strat_mix":{"0":23,"1":6,"2":18},"representatives":[{"match_id":"0fc0d9a2-b14b-4670-86de-0074af3e9b70","round_number":9},{"match_id":"0fc0d9a2-b14b-4670-86de-0074af3e9b70","round_number":10},{"match_id":"0fc0d9a2-b14b-4670-86de-0074af3e9b70","round_number":11}]},{"side":"T","type":"flash","cluster_id":1,"label":"Bridge","det_rx":492.8763,"det_ry":604.8843,"throw_rx":429.11835,"throw_ry":719.2109,"count":41,"share":0.15438388,"t_avg":20.200838,"t_std":20.043484,"strat_mix":{"0":23,"1":14,"2":4},"representatives":[{"match_id":"0fc0d9a2-b14b-4670-86de-0074af3e9b70","round_number":11},{"match_id":"0fc0d9a2-b14b-4670-86de-0074af3e9b70","round_number":12},{"match_id":"0fc0d9a2-b14b-4670-86de-0074af3e9b70","round_number":13}]},{"side":"T","type":"flash","cluster_id":2,"label":"Main","det_rx":819.4816,"det_ry":479.22083,"throw_rx":755.1381,"throw_ry":649.0478,"count":33,"share":0.12973599,"t_avg":27.746685,"t_std":26.602455,"strat_mix":{"0":13,"1":14,"2":6},"representatives":[{"match_id":"0fc0d9a2-b14b-4670-86de-0074af3e9b70","round_number":9},{"match_id":"0fc0d9a2-b14b-4670-86de-0074af3e9b70","round_number":17},{"match_id":"0fc0d9a2-b14b-4670-86de-0074af3e9b70","round_number":18}]},{"side":"T","type":"flash","cluster_id":3,"label":"MidDoors","det_rx":533.90466,"det_ry":519.3767,"throw_rx":504.5464,"throw_ry":690.0521,"count":25,"share":0.090923436,"t_avg":46.490623,"t_std":12.664229,"strat_mix":{"0":19,"1":5,"2":1},"representatives":[{"match_id":"0fc0d9a2-b14b-4670-86de-0074af3e9b70","round_number":18},{"match_id":"0fc0d9a2-b14b-4670-86de-0074af3e9b70","round_number":18},{"match_id":"5535bc94-71f3-4258-843e-8c54c19191ab","round_number":17}]},{"side":"T","type":"flash","cluster_id":4,"label":"BombsiteA","det_rx":761.6333,"det_ry":343.93945,"throw_rx":702.0332,"throw_ry":498.9973,"count":25,"share":0.08359464,"t_avg":66.929375,"t_std":23.563707,"strat_mix":{"0":16,"1":8,"2":1},"representatives":[{"match_id":"0fc0d9a2-b14b-4670-86de-0074af3e9b70","round_number":10},{"match_id":"0fc0d9a2-b14b-4670-86de-0074af3e9b70","round_number":10},{"match_id":"0fc0d9a2-b14b-4670-86de-0074af3e9b70","round_number":15}]},{"side":"T","type":"flash","cluster_id":5,"label":"Canal","det_rx":613.80023,"det_ry":628.58795,"throw_rx":721.79895,"throw_ry":685.06964,"count":18,"share":0.06954932,"t_avg":9.907118,"t_std":3.6778154,"strat_mix":{"0":12,"1":3,"2":3},"representatives":[{"match_id":"0fc0d9a2-b14b-4670-86de-0074af3e9b70","round_number":12},{"match_id":"0fc0d9a2-b14b-4670-86de-0074af3e9b70","round_number":18},{"match_id":"0fc0d9a2-b14b-4670-86de-0074af3e9b70","round_number":19}]},{"side":"T","type":"flash","cluster_id":6,"label":"Walkway","det_rx":660.3397,"det_ry":379.8209,"throw_rx":711.45276,"throw_ry":454.83438,"count":14,"share":0.052913822,"t_avg":62.5904,"t_std":17.14974,"strat_mix":{"0":7,"1":6,"2":1},"representatives":[{"match_id":"0fc0d9a2-b14b-4670-86de-0074af3e9b70","round_number":19},{"match_id":"5aeefed0-dd87-4bc6-aeb5-be29a086cf2b","round_number":7},{"match_id":"5aeefed0-dd87-4bc6-aeb5-be29a086cf2b","round_number":10}]},{"side":"T","type":"flash","cluster_id":7,"label":"Fountain","det_rx":863.6813,"det_ry":273.43112,"throw_rx":820.33234,"throw_ry":433.32132,"count":16,"share":0.04940085,"t_avg":57.061523,"t_std":18.833044,"strat_mix":{"0":9,"1":6,"2":1},"representatives":[{"match_id":"5535bc94-71f3-4258-843e-8c54c19191ab","round_number":21},{"match_id":"5535bc94-71f3-4258-843e-8c54c19191ab","round_number":21},{"match_id":"5aeefed0-dd87-4bc6-aeb5-be29a086cf2b","round_number":8}]},{"side":"T","type":"flash","cluster_id":8,"label":"BackofB","det_rx":414.60886,"det_ry":528.1159,"throw_rx":280.37244,"throw_ry":598.60956,"count":10,"share":0.035770394,"t_avg":60.98594,"t_std":22.282032,"strat_mix":{"0":7,"1":1,"2":2},"representatives":[{"match_id":"0fc0d9a2-b14b-4670-86de-0074af3e9b70","round_number":14},{"match_id":"0fc0d9a2-b14b-4670-86de-0074af3e9b70","round_number":19},{"match_id":"5535bc94-71f3-4258-843e-8c54c19191ab","round_number":17}]},{"side":"T","type":"flash","cluster_id":9,"label":"Alley","det_rx":305.77548,"det_ry":449.13516,"throw_rx":330.3883,"throw_ry":599.41156,"count":9,"share":0.03004046,"t_avg":67.954865,"t_std":22.699684,"strat_mix":{"0":4,"1":1,"2":4},"representatives":[{"match_id":"0fc0d9a2-b14b-4670-86de-0074af3e9b70","round_number":14},{"match_id":"0fc0d9a2-b14b-4670-86de-0074af3e9b70","round_number":18},{"match_id":"0fc0d9a2-b14b-4670-86de-0074af3e9b70","round_number":18}]},{"side":"T","type":"flash","cluster_id":10,"label":"Main","det_rx":758.6934,"det_ry":467.95163,"throw_rx":759.4274,"throw_ry":549.67834,"count":7,"share":0.029318254,"t_avg":40.92857,"t_std":41.878784,"strat_mix":{"0":4,"1":2,"2":1},"representatives":[{"match_id":"0fc0d9a2-b14b-4670-86de-0074af3e9b70","round_number":13},{"match_id":"5aeefed0-dd87-4bc6-aeb5-be29a086cf2b","round_number":7},{"match_id":"69eab253-3780-4898-8e5a-3556b2a95d87","round_number":4}]},{"side":"T","type":"flash","cluster_id":11,"label":"Canal","det_rx":684.7959,"det_ry":603.48956,"throw_rx":698.44604,"throw_ry":710.4208,"count":7,"share":0.027189678,"t_avg":18.223215,"t_std":12.296274,"strat_mix":{"0":2,"1":4,"2":1},"representatives":[{"match_id":"4f7a6e3b-4ca2-4580-a0d2-8b199290228b","round_number":15},{"match_id":"5535bc94-71f3-4258-843e-8c54c19191ab","round_number":15},{"match_id":"69eab253-3780-4898-8e5a-3556b2a95d87","round_number":8}]},{"side":"T","type":"flash","cluster_id":12,"label":"Connector","det_rx":365.4268,"det_ry":590.444,"throw_rx":410.8199,"throw_ry":630.59436,"count":7,"share":0.02483795,"t_avg":55.263393,"t_std":17.586073,"strat_mix":{"0":3,"1":3,"2":1},"representatives":[{"match_id":"0fc0d9a2-b14b-4670-86de-0074af3e9b70","round_number":14},{"match_id":"4f7a6e3b-4ca2-4580-a0d2-8b199290228b","round_number":14},{"match_id":"5aeefed0-dd87-4bc6-aeb5-be29a086cf2b","round_number":5}]},{"side":"T","type":"flash","cluster_id":13,"label":"Main","det_rx":872.3593,"det_ry":391.4909,"throw_rx":778.78357,"throw_ry":396.5717,"count":6,"share":0.01361165,"t_avg":69.1224,"t_std":34.40682,"strat_mix":{"0":2,"1":4},"representatives":[{"match_id":"5535bc94-71f3-4258-843e-8c54c19191ab","round_number":21},{"match_id":"5535bc94-71f3-4258-843e-8c54c19191ab","round_number":21},{"match_id":"69eab253-3780-4898-8e5a-3556b2a95d87","round_number":4}]},{"side":"T","type":"flash","cluster_id":14,"label":"Middle","det_rx":582.3944,"det_ry":450.9575,"throw_rx":490.9324,"throw_ry":623.43036,"count":3,"share":0.013358011,"t_avg":44.401043,"t_std":7.4600754,"strat_mix":{"0":1,"1":2},"representatives":[{"match_id":"69eab253-3780-4898-8e5a-3556b2a95d87","round_number":29},{"match_id":"7c4ae662-d2f9-4aab-bcab-49c8d69bddbf","round_number":8},{"match_id":"7c4ae662-d2f9-4aab-bcab-49c8d69bddbf","round_number":10}]},{"side":"T","type":"flash","cluster_id":15,"label":"BombsiteB","det_rx":220.24667,"det_ry":490.87177,"throw_rx":246.20544,"throw_ry":659.96924,"count":4,"share":0.010544911,"t_avg":40.375,"t_std":23.59489,"strat_mix":{"0":1,"2":3},"representatives":[{"match_id":"5aeefed0-dd87-4bc6-aeb5-be29a086cf2b","round_number":11},{"match_id":"8d7d81b8-fe5c-4a31-a6c6-683dbb5971c4","round_number":18},{"match_id":"d6284f93-fab2-49fe-b784-e6b1459a8a77","round_number":13}]},{"side":"T","type":"he","cluster_id":0,"label":"Main","det_rx":834.1962,"det_ry":425.20673,"throw_rx":756.91144,"throw_ry":463.38025,"count":22,"share":0.1906297,"t_avg":53.636364,"t_std":33.092525,"strat_mix":{"0":12,"1":9,"2":1},"representatives":[{"match_id":"0fc0d9a2-b14b-4670-86de-0074af3e9b70","round_number":19},{"match_id":"0fc0d9a2-b14b-4670-86de-0074af3e9b70","round_number":19},{"match_id":"5535bc94-71f3-4258-843e-8c54c19191ab","round_number":16}]},{"side":"T","type":"he","cluster_id":1,"label":"MidDoors","det_rx":573.7518,"det_ry":558.99316,"throw_rx":439.87625,"throw_ry":729.85956,"count":25,"share":0.16923471,"t_avg":21.06875,"t_std":13.050693,"strat_mix":{"0":14,"1":10,"2":1},"representatives":[{"match_id":"0fc0d9a2-b14b-4670-86de-0074af3e9b70","round_number":10},{"match_id":"0fc0d9a2-b14b-4670-86de-0074af3e9b70","round_number":11},{"match_id":"0fc0d9a2-b14b-4670-86de-0074af3e9b70","round_number":12}]},{"side":"T","type":"he","cluster_id":2,"label":"OutsideLong","det_rx":231.95256,"det_ry":571.93005,"throw_rx":265.8566,"throw_ry":680.78613,"count":11,"share":0.08526517,"t_avg":35.071022,"t_std":19.625599,"strat_mix":{"0":6,"1":1,"2":4},"representatives":[{"match_id":"0fc0d9a2-b14b-4670-86de-0074af3e9b70","round_number":10},{"match_id":"0fc0d9a2-b14b-4670-86de-0074af3e9b70","round_number":11},{"match_id":"5535bc94-71f3-4258-843e-8c54c19191ab","round_number":18}]},{"side":"T","type":"he","cluster_id":3,"label":"Bricks","det_rx":378.177,"det_ry":435.09293,"throw_rx":259.05902,"throw_ry":581.93463,"count":9,"share":0.07585079,"t_avg":44.699654,"t_std":19.036247,"strat_mix":{"0":2,"1":1,"2":6},"representatives":[{"match_id":"0fc0d9a2-b14b-4670-86de-0074af3e9b70","round_number":12},{"match_id":"5aeefed0-dd87-4bc6-aeb5-be29a086cf2b","round_number":9},{"match_id":"5aeefed0-dd87-4bc6-aeb5-be29a086cf2b","round_number":9}]},{"side":"T","type":"he","cluster_id":4,"label":"Bridge","det_rx":479.2101,"det_ry":601.94446,"throw_rx":381.48685,"throw_ry":611.29333,"count":8,"share":0.06916457,"t_avg":61.78711,"t_std":30.569437,"strat_mix":{"0":5,"1":2,"2":1},"representatives":[{"match_id":"0fc0d9a2-b14b-4670-86de-0074af3e9b70","round_number":13},{"match_id":"4f7a6e3b-4ca2-4580-a0d2-8b199290228b","round_number":16},{"match_id":"5aeefed0-dd87-4bc6-aeb5-be29a086cf2b","round_number":4}]},{"side":"T","type":"he","cluster_id":5,"label":"BackofB","det_rx":400.10574,"det_ry":518.63916,"throw_rx":272.9065,"throw_ry":572.09863,"count":8,"share":0.06768912,"t_avg":80.33984,"t_std":16.707525,"strat_mix":{"0":5,"1":3},"representatives":[{"match_id":"0fc0d9a2-b14b-4670-86de-0074af3e9b70","round_number":11},{"match_id":"5aeefed0-dd87-4bc6-aeb5-be29a086cf2b","round_number":5},{"match_id":"69eab253-3780-4898-8e5a-3556b2a95d87","round_number":3}]},{"side":"T","type":"he","cluster_id":6,"label":"MidDoors","det_rx":557.2138,"det_ry":480.73648,"throw_rx":518.5154,"throw_ry":641.79956,"count":7,"share":0.057256334,"t_avg":39.035713,"t_std":19.34249,"strat_mix":{"0":3,"1":1,"2":3},"representatives":[{"match_id":"5535bc94-71f3-4258-843e-8c54c19191ab","round_number":18},{"match_id":"5aeefed0-dd87-4bc6-aeb5-be29a086cf2b","round_number":7},{"match_id":"69eab253-3780-4898-8e5a-3556b2a95d87","round_number":11}]},{"side":"T","type":"he","cluster_id":7,"label":"Walkway","det_rx":717.61346,"det_ry":324.89233,"throw_rx":710.5337,"throw_ry":392.16895,"count":6,"share":0.052220073,"t_avg":76.458336,"t_std":18.649012,"strat_mix":{"1":4,"2":2},"representatives":[{"match_id":"69eab253-3780-4898-8e5a-3556b2a95d87","round_number":5},{"match_id":"69eab253-3780-4898-8e5a-3556b2a95d87","round_number":9},{"match_id":"7c4ae662-d2f9-4aab-bcab-49c8d69bddbf","round_number":7}]},{"side":"T","type":"he","cluster_id":8,"label":"Heaven","det_rx":735.8121,"det_ry":254.92229,"throw_rx":863.3569,"throw_ry":345.6158,"count":7,"share":0.050317496,"t_avg":57.546875,"t_std":24.540249,"strat_mix":{"0":3,"1":4},"representatives":[{"match_id":"0fc0d9a2-b14b-4670-86de-0074af3e9b70","round_number":17},{"match_id":"0fc0d9a2-b14b-4670-86de-0074af3e9b70","round_number":19},{"match_id":"5aeefed0-dd87-4bc6-aeb5-be29a086cf2b","round_number":10}]},{"side":"T","type":"he","cluster_id":9,"label":"BombsiteB","det_rx":312.42603,"det_ry":556.9869,"throw_rx":246.2061,"throw_ry":618.3886,"count":6,"share":0.043091178,"t_avg":66.34115,"t_std":18.385498,"strat_mix":{"0":3,"1":2,"2":1},"representatives":[{"match_id":"0fc0d9a2-b14b-4670-86de-0074af3e9b70","round_number":12},{"match_id":"5535bc94-71f3-4258-843e-8c54c19191ab","round_number":19},{"match_id":"5aeefed0-dd87-4bc6-aeb5-be29a086cf2b","round_number":5}]},{"side":"T","type":"he","cluster_id":10,"label":"Fountain","det_rx":861.37756,"det_ry":266.88235,"throw_rx":831.40466,"throw_ry":449.45142,"count":6,"share":0.039145574,"t_avg":54.666668,"t_std":10.030904,"strat_mix":{"0":4,"1":2},"representatives":[{"match_id":"4f7a6e3b-4ca2-4580-a0d2-8b199290228b","round_number":17},{"match_id":"5535bc94-71f3-4258-843e-8c54c19191ab","round_number":18},{"match_id":"5535bc94-71f3-4258-843e-8c54c19191ab","round_number":21}]},{"side":"T","type":"he","cluster_id":11,"label":"Main","det_rx":787.36194,"det_ry":472.4663,"throw_rx":756.82526,"throw_ry":596.25214,"count":4,"share":0.03261785,"t_avg":15.2890625,"t_std":2.2315185,"strat_mix":{"0":3,"1":1},"representatives":[{"match_id":"69eab253-3780-4898-8e5a-3556b2a95d87","round_number":30},{"match_id":"7c4ae662-d2f9-4aab-bcab-49c8d69bddbf","round_number":11},{"match_id":"7c4ae662-d2f9-4aab-bcab-49c8d69bddbf","round_number":11}]},{"side":"T","type":"he","cluster_id":12,"label":"Walkway","det_rx":656.9513,"det_ry":393.03937,"throw_rx":695.61194,"throw_ry":422.6339,"count":3,"share":0.028964566,"t_avg":48.833332,"t_std":29.804028,"strat_mix":{"0":2,"1":1},"representatives":[{"match_id":"5aeefed0-dd87-4bc6-aeb5-be29a086cf2b","round_number":5},{"match_id":"5aeefed0-dd87-4bc6-aeb5-be29a086cf2b","round_number":10},{"match_id":"69eab253-3780-4898-8e5a-3556b2a95d87","round_number":30}]},{"side":"T","type":"molotov","cluster_id":0,"label":"MidDoors","det_rx":578.52563,"det_ry":531.7318,"throw_rx":452.14752,"throw_ry":706.2841,"count":48,"share":0.21859287,"t_avg":29.37858,"t_std":19.252893,"strat_mix":{"0":25,"1":20,"2":3},"representatives":[{"match_id":"0fc0d9a2-b14b-4670-86de-0074af3e9b70","round_number":10},{"match_id":"0fc0d9a2-b14b-4670-86de-0074af3e9b70","round_number":11},{"match_id":"0fc0d9a2-b14b-4670-86de-0074af3e9b70","round_number":13}]},{"side":"T","type":"molotov","cluster_id":1,"label":"BackofB","det_rx":418.79562,"det_ry":517.67847,"throw_rx":235.49127,"throw_ry":589.91724,"count":17,"share":0.075104475,"t_avg":54.613052,"t_std":26.815498,"strat_mix":{"0":6,"1":3,"2":8},"representatives":[{"match_id":"0fc0d9a2-b14b-4670-86de-0074af3e9b70","round_number":14},{"match_id":"0fc0d9a2-b14b-4670-86de-0074af3e9b70","round_number":14},{"match_id":"0fc0d9a2-b14b-4670-86de-0074af3e9b70","round_number":17}]},{"side":"T","type":"molotov","cluster_id":2,"label":"Connector","det_rx":393.25934,"det_ry":577.2452,"throw_rx":417.64673,"throw_ry":585.40094,"count":14,"share":0.07418649,"t_avg":51.72433,"t_std":21.442608,"strat_mix":{"0":6,"1":6,"2":2},"representatives":[{"match_id":"0fc0d9a2-b14b-4670-86de-0074af3e9b70","round_number":11},{"match_id":"0fc0d9a2-b14b-4670-86de-0074af3e9b70","round_number":18},{"match_id":"5aeefed0-dd87-4bc6-aeb5-be29a086cf2b","round_number":5}]},{"side":"T","type":"molotov","cluster_id":3,"label":"Main","det_rx":769.3948,"det_ry":467.66336,"throw_rx":761.8314,"throw_ry":592.5167,"count":14,"share":0.073652536,"t_avg":14.6875,"t_std":4.066151,"strat_mix":{"0":9,"1":1,"2":4},"representatives":[{"match_id":"0fc0d9a2-b14b-4670-86de-0074af3e9b70","round_number":13},{"match_id":"5aeefed0-dd87-4bc6-aeb5-be29a086cf2b","round_number":6},{"match_id":"5aeefed0-dd87-4bc6-aeb5-be29a086cf2b","round_number":7}]},{"side":"T","type":"molotov","cluster_id":4,"label":"BombsiteB","det_rx":322.5393,"det_ry":575.27075,"throw_rx":270.2533,"throw_ry":683.53937,"count":14,"share":0.06368971,"t_avg":41.155132,"t_std":26.510714,"strat_mix":{"0":11,"1":1,"2":2},"representatives":[{"match_id":"0fc0d9a2-b14b-4670-86de-0074af3e9b70","round_number":10},{"match_id":"0fc0d9a2-b14b-4670-86de-0074af3e9b70","round_number":11},{"match_id":"0fc0d9a2-b14b-4670-86de-0074af3e9b70","round_number":12}]},{"side":"T","type":"molotov","cluster_id":5,"label":"Heaven","det_rx":743.99786,"det_ry":246.30429,"throw_rx":784.7734,"throw_ry":433.68823,"count":12,"share":0.061095625,"t_avg":57.09505,"t_std":25.178066,"strat_mix":{"0":8,"1":4},"representatives":[{"match_id":"0fc0d9a2-b14b-4670-86de-0074af3e9b70","round_number":17},{"match_id":"4f7a6e3b-4ca2-4580-a0d2-8b199290228b","round_number":13},{"match_id":"5535bc94-71f3-4258-843e-8c54c19191ab","round_number":21}]},{"side":"T","type":"molotov","cluster_id":6,"label":"Main","det_rx":833.64844,"det_ry":458.47952,"throw_rx":718.89923,"throw_ry":502.8317,"count":12,"share":0.057729557,"t_avg":21.221354,"t_std":28.12928,"strat_mix":{"0":3,"1":9},"representatives":[{"match_id":"0fc0d9a2-b14b-4670-86de-0074af3e9b70","round_number":14},{"match_id":"5aeefed0-dd87-4bc6-aeb5-be29a086cf2b","round_number":5},{"match_id":"5aeefed0-dd87-4bc6-aeb5-be29a086cf2b","round_number":12}]},{"side":"T","type":"molotov","cluster_id":7,"label":"Bricks","det_rx":381.31155,"det_ry":414.61597,"throw_rx":249.72165,"throw_ry":587.18805,"count":10,"share":0.05547093,"t_avg":59.12031,"t_std":26.351816,"strat_mix":{"0":5,"1":1,"2":4},"representatives":[{"match_id":"0fc0d9a2-b14b-4670-86de-0074af3e9b70","round_number":11},{"match_id":"5aeefed0-dd87-4bc6-aeb5-be29a086cf2b","round_number":1},{"match_id":"5aeefed0-dd87-4bc6-aeb5-be29a086cf2b","round_number":4}]},{"side":"T","type":"molotov","cluster_id":8,"label":"Fountain","det_rx":860.5876,"det_ry":274.42374,"throw_rx":823.8871,"throw_ry":449.7798,"count":11,"share":0.054633293,"t_avg":60.085228,"t_std":16.511322,"strat_mix":{"0":8,"1":3},"representatives":[{"match_id":"0fc0d9a2-b14b-4670-86de-0074af3e9b70","round_number":10},{"match_id":"4f7a6e3b-4ca2-4580-a0d2-8b199290228b","round_number":16},{"match_id":"5535bc94-71f3-4258-843e-8c54c19191ab","round_number":16}]},{"side":"T","type":"molotov","cluster_id":9,"label":"Walkway","det_rx":696.1948,"det_ry":341.17627,"throw_rx":775.1232,"throw_ry":484.939,"count":12,"share":0.05238216,"t_avg":56.68099,"t_std":22.125767,"strat_mix":{"0":8,"1":4},"representatives":[{"match_id":"0fc0d9a2-b14b-4670-86de-0074af3e9b70","round_number":19},{"match_id":"0fc0d9a2-b14b-4670-86de-0074af3e9b70","round_number":19},{"match_id":"5535bc94-71f3-4258-843e-8c54c19191ab","round_number":14}]},{"side":"T","type":"molotov","cluster_id":10,"label":"Walkway","det_rx":648.8852,"det_ry":391.06937,"throw_rx":703.8783,"throw_ry":481.19397,"count":9,"share":0.04700595,"t_avg":57.975693,"t_std":10.789128,"strat_mix":{"0":6,"1":3},"representatives":[{"match_id":"0fc0d9a2-b14b-4670-86de-0074af3e9b70","round_number":18},{"match_id":"5535bc94-71f3-4258-843e-8c54c19191ab","round_number":18},{"match_id":"5aeefed0-dd87-4bc6-aeb5-be29a086cf2b","round_number":6}]},{"side":"T","type":"molotov","cluster_id":11,"label":"MidDoors","det_rx":530.3063,"det_ry":477.45963,"throw_rx":484.16144,"throw_ry":720.629,"count":8,"share":0.03481653,"t_avg":29.066406,"t_std":11.567729,"strat_mix":{"0":3,"1":4,"2":1},"representatives":[{"match_id":"0fc0d9a2-b14b-4670-86de-0074af3e9b70","round_number":11},{"match_id":"0fc0d9a2-b14b-4670-86de-0074af3e9b70","round_number":17},{"match_id":"5535bc94-71f3-4258-843e-8c54c19191ab","round_number":18}]},{"side":"T","type":"molotov","cluster_id":12,"label":"Main","det_rx":830.19543,"det_ry":420.04166,"throw_rx":740.695,"throw_ry":421.44385,"count":6,"share":0.028134221,"t_avg":57.973957,"t_std":30.859537,"strat_mix":{"0":3,"1":3},"representatives":[{"match_id":"5aeefed0-dd87-4bc6-aeb5-be29a086cf2b","round_number":10},{"match_id":"5aeefed0-dd87-4bc6-aeb5-be29a086cf2b","round_number":11},{"match_id":"69eab253-3780-4898-8e5a-3556b2a95d87","round_number":9}]},{"side":"T","type":"molotov","cluster_id":13,"label":"Middle","det_rx":579.7347,"det_ry":326.81573,"throw_rx":547.7721,"throw_ry":508.65872,"count":3,"share":0.017583417,"t_avg":48.020832,"t_std":13.737129,"strat_mix":{"0":1,"1":1,"2":1},"representatives":[{"match_id":"5aeefed0-dd87-4bc6-aeb5-be29a086cf2b","round_number":6},{"match_id":"7c4ae662-d2f9-4aab-bcab-49c8d69bddbf","round_number":7},{"match_id":"7c4ae662-d2f9-4aab-bcab-49c8d69bddbf","round_number":8}]},{"side":"T","type":"molotov","cluster_id":14,"label":"Heaven","det_rx":688.30457,"det_ry":275.67508,"throw_rx":794.8042,"throw_ry":281.81564,"count":3,"share":0.0077659376,"t_avg":78.635414,"t_std":7.86909,"strat_mix":{"0":3},"representatives":[{"match_id":"0fc0d9a2-b14b-4670-86de-0074af3e9b70","round_number":19},{"match_id":"5535bc94-71f3-4258-843e-8c54c19191ab","round_number":16},{"match_id":"8d7d81b8-fe5c-4a31-a6c6-683dbb5971c4","round_number":21}]},{"side":"T","type":"smoke","cluster_id":0,"label":"Bridge","det_rx":446.41403,"det_ry":625.35016,"throw_rx":475.17194,"throw_ry":926.26776,"count":43,"share":0.18830584,"t_avg":5.973474,"t_std":11.61182,"strat_mix":{"0":25,"1":10,"2":8},"representatives":[{"match_id":"0fc0d9a2-b14b-4670-86de-0074af3e9b70","round_number":11},{"match_id":"0fc0d9a2-b14b-4670-86de-0074af3e9b70","round_number":11},{"match_id":"0fc0d9a2-b14b-4670-86de-0074af3e9b70","round_number":12}]},{"side":"T","type":"smoke","cluster_id":1,"label":"Main","det_rx":851.32556,"det_ry":374.30402,"throw_rx":732.77856,"throw_ry":663.45575,"count":37,"share":0.13740388,"t_avg":20.297297,"t_std":17.553272,"strat_mix":{"0":19,"1":14,"2":4},"representatives":[{"match_id":"0fc0d9a2-b14b-4670-86de-0074af3e9b70","round_number":10},{"match_id":"0fc0d9a2-b14b-4670-86de-0074af3e9b70","round_number":13},{"match_id":"0fc0d9a2-b14b-4670-86de-0074af3e9b70","round_number":14}]},{"side":"T","type":"smoke","cluster_id":2,"label":"BombsiteB","det_rx":304.06552,"det_ry":482.3781,"throw_rx":287.4324,"throw_ry":711.93695,"count":34,"share":0.12911567,"t_avg":44.163605,"t_std":27.900728,"strat_mix":{"0":18,"1":7,"2":9},"representatives":[{"match_id":"0fc0d9a2-b14b-4670-86de-0074af3e9b70","round_number":10},{"match_id":"0fc0d9a2-b14b-4670-86de-0074af3e9b70","round_number":11},{"match_id":"0fc0d9a2-b14b-4670-86de-0074af3e9b70","round_number":12}]},{"side":"T","type":"smoke","cluster_id":3,"label":"MidDoors","det_rx":526.36993,"det_ry":481.6601,"throw_rx":471.82858,"throw_ry":728.262,"count":34,"share":0.11990951,"t_avg":29.677849,"t_std":8.1440115,"strat_mix":{"0":26,"1":8},"representatives":[{"match_id":"0fc0d9a2-b14b-4670-86de-0074af3e9b70","round_number":10},{"match_id":"0fc0d9a2-b14b-4670-86de-0074af3e9b70","round_number":12},{"match_id":"0fc0d9a2-b14b-4670-86de-0074af3e9b70","round_number":13}]},{"side":"T","type":"smoke","cluster_id":4,"label":"BombsiteB","det_rx":259.63193,"det_ry":543.8128,"throw_rx":348.02972,"throw_ry":864.9765,"count":24,"share":0.09413143,"t_avg":4.546875,"t_std":1.3096524,"strat_mix":{"0":16,"1":2,"2":6},"representatives":[{"match_id":"0fc0d9a2-b14b-4670-86de-0074af3e9b70","round_number":12},{"match_id":"0fc0d9a2-b14b-4670-86de-0074af3e9b70","round_number":15},{"match_id":"0fc0d9a2-b14b-4670-86de-0074af3e9b70","round_number":19}]},{"side":"T","type":"smoke","cluster_id":5,"label":"Walkway","det_rx":646.8124,"det_ry":389.1024,"throw_rx":746.8184,"throw_ry":473.44684,"count":17,"share":0.0669786,"t_avg":50.273895,"t_std":21.807613,"strat_mix":{"0":8,"1":9},"representatives":[{"match_id":"0fc0d9a2-b14b-4670-86de-0074af3e9b70","round_number":10},{"match_id":"0fc0d9a2-b14b-4670-86de-0074af3e9b70","round_number":19},{"match_id":"4f7a6e3b-4ca2-4580-a0d2-8b199290228b","round_number":15}]},{"side":"T","type":"smoke","cluster_id":6,"label":"Heaven","det_rx":731.8531,"det_ry":206.4161,"throw_rx":753.0323,"throw_ry":485.9575,"count":17,"share":0.06628075,"t_avg":51.326286,"t_std":13.963554,"strat_mix":{"0":9,"1":8},"representatives":[{"match_id":"0fc0d9a2-b14b-4670-86de-0074af3e9b70","round_number":17},{"match_id":"0fc0d9a2-b14b-4670-86de-0074af3e9b70","round_number":19},{"match_id":"4f7a6e3b-4ca2-4580-a0d2-8b199290228b","round_number":13}]},{"side":"T","type":"smoke","cluster_id":7,"label":"Bricks","det_rx":359.58633,"det_ry":423.48724,"throw_rx":326.282,"throw_ry":592.8396,"count":15,"share":0.059308413,"t_avg":60.752083,"t_std":30.203466,"strat_mix":{"0":7,"1":4,"2":4},"representatives":[{"match_id":"0fc0d9a2-b14b-4670-86de-0074af3e9b70","round_number":9},{"match_id":"0fc0d9a2-b14b-4670-86de-0074af3e9b70","round_number":17},{"match_id":"0fc0d9a2-b14b-4670-86de-0074af3e9b70","round_number":17}]},{"side":"T","type":"smoke","cluster_id":8,"label":"PalaceInterior","det_rx":541.65515,"det_ry":335.67664,"throw_rx":659.24194,"throw_ry":554.4348,"count":12,"share":0.04323918,"t_avg":59.566406,"t_std":11.539298,"strat_mix":{"0":7,"1":5},"representatives":[{"match_id":"0fc0d9a2-b14b-4670-86de-0074af3e9b70","round_number":10},{"match_id":"0fc0d9a2-b14b-4670-86de-0074af3e9b70","round_number":13},{"match_id":"0fc0d9a2-b14b-4670-86de-0074af3e9b70","round_number":18}]},{"side":"T","type":"smoke","cluster_id":9,"label":"Connector","det_rx":401.3115,"det_ry":590.5052,"throw_rx":453.72693,"throw_ry":811.13916,"count":11,"share":0.03503335,"t_avg":24.826704,"t_std":33.861675,"strat_mix":{"0":7,"1":3,"2":1},"representatives":[{"match_id":"5535bc94-71f3-4258-843e-8c54c19191ab","round_number":16},{"match_id":"69eab253-3780-4898-8e5a-3556b2a95d87","round_number":10},{"match_id":"69eab253-3780-4898-8e5a-3556b2a95d87","round_number":30}]},{"side":"T","type":"smoke","cluster_id":10,"label":"Main","det_rx":795.4312,"det_ry":477.2267,"throw_rx":824.94196,"throw_ry":440.5085,"count":4,"share":0.014403588,"t_avg":72.80859,"t_std":39.415016,"strat_mix":{"0":2,"1":2},"representatives":[{"match_id":"5535bc94-71f3-4258-843e-8c54c19191ab","round_number":15},{"match_id":"5535bc94-71f3-4258-843e-8c54c19191ab","round_number":20},{"match_id":"5aeefed0-dd87-4bc6-aeb5-be29a086cf2b","round_number":7}]},{"side":"T","type":"smoke","cluster_id":11,"label":"Walkway","det_rx":687.8726,"det_ry":313.82465,"throw_rx":723.86017,"throw_ry":477.6562,"count":3,"share":0.0092808725,"t_avg":73.010414,"t_std":11.03292,"strat_mix":{"0":1,"1":2},"representatives":[{"match_id":"5aeefed0-dd87-4bc6-aeb5-be29a086cf2b","round_number":10},{"match_id":"8d7d81b8-fe5c-4a31-a6c6-683dbb5971c4","round_number":16},{"match_id":"d6284f93-fab2-49fe-b784-e6b1459a8a77","round_number":15}]}]}
